Workbook

Sheet Legend
B3: Assessment of Criteria | C3: Value for Average Calculation | D3: Explanation
B4: High | C4: 3 | D4: Significant/Critical
B5: Medium | C5: 2 | D5: Major
B6: Low | C6: 1 | D6: Minor
B7: n/a | C7: n/a | D7: No information available, not assessed, therefore no influence on the average calculation. Rationale is obligatory.

Sheet Audit conclusion
B1: Audit Conclusion
B3: Audit No. | D3: 2025-045 Cyber and Information Security
AK4: IT applications list in golden source needs to be updated AS well | AX4: DA repository
B5: Audit Universe | E5: Applicable Legal Entity (Please define all Legal Entities in scope of the audit) | Q5: Inherent Risk Assessment OpRisk cells filled through risk assessment tabs | W5: Final Inherent Risk after the performed audit | AA5: Regulatory required audit frequency | AC5: Suggested CMI | AE5: Residual Risk | AF5: Proposed changes to RCA or Audit Universe after the audit | AH5: Mapping of relevant L2 to ICS processes | AK5: Relevant IT Applications of L2 | AX5: Data Analytics
D6: (Put whole name of the audit object: AU-XXX-XXX-Name of the process) | E6: Please indicate below for which legal entity the information and assessment is relevant for. | Q6: All assigned scores are ordinally in relation to the other L2 processes within the audit universe. The scores are purely IA Judgement. | W6: Final Inherent value is the maximum value of the assessed risk categories and can be High, Medium or Low | AA6: Please only indicate if and what regulation detail is driving audit frequency of L2. Also precise if LE specificities and LE without regulatory requirements | AC6: Considering audit testing and results, and SIIs, how would you rate the control maturity of the L2 process (Weak/undefined, Developed, Strong/Robust). Please indicate decision for suggested CMI | AE6: Residual Risk (RR) is automatically calculated by applying CMI to the final Inherent Risk (IR). | AF6: E.g. L2 name change, L2 split, consolidation, new L2 Amended test approach, controls, risks, further. Please indicate reason for proposed changes. Maximum number of characters for the process name is 89. | AH6: Please indicate ICS process landscape reference. Please indicate if mapping is complete/partial/spread over multiple ICS processes. If multiple, list the ICS processes with "/" as separator | AK6: Please indicate the application code from APMS (like RTS (AID024)) | AX6: Please indicate the eligibility of the L2 process for data analytics with respective rationale. If eligible, please fill in the DA repository and input the reference to specific repository line/test
B7: L0 Process Area | C7: AO ID | D7: L2 Process (AU-XXX-XXX-Process name) | E7: DBAG | F7: ExR | G7: EFAG | H7: ECAG | I7: CBF | J7: CH | K7: CBL | L7: LuxCSD | M7: CS | N7: CI | O7: CFCL | Q7: Internal People & Staff | R7: Processes | S7: Internal Systems | T7: External | U7: IS Risk assessment | W7: Final Inherent risk | Y7: Comment (Mandatory comment for the justification of the all inhernet risk assessment, specify if there is anything specific) | AA7: Frequency | AB7: Comment | AC7: CMI | AD7: Comment | AE7: Residual risk | AF7: Changes to RCA/AU | AG7: Comment | AH7: Mapping L2 to ICS | AI7: Comment | AK7: MISP (AID737) | AL7: PKI DBAG (AID1064) | AM7: PKI MSCA (AID1065) | AN7: PKI Clearstream (AID1066) | AO7: Gpg4Win (AID591) | AP7: CrowdStrike Falcon Complete (AID2131) | AQ7: PA CNAPP (AID2146) | AR7: RPE (AID953) | AS7: Rapid7 Nexpose (AID986) | AT7: VMT & Risk Register (AID430) | AU7: Dataminr(to be added to APMS) | AV7: IT applications list in Golden Source is updated | AX7: Applied DA (yes/no) Validation field with "Yes" or "No" | AY7: Rationale if not eligible | AZ7: DA repository reference
B8: Support | C8: 1 | D8: AU-109-02-Cyber & IS Strategy and Design | E8: X | F8: X | G8: X | H8: X | I8: X | J8: X | K8: X | L8: X | M8: X | N8: X | O8: X | Q8: =IF('Internal People & Staff'!E$13>0,'Internal People & Staff'!E$13,'Internal People & Staff'!E$11) -> Medium | R8: =IF(Processes!E$12>0,Processes!E$12,Processes!E$10) -> Medium | S8: =IF('Internal Systems'!E$12>0,'Internal Systems'!E$12,'Internal Systems'!E$10) -> Low | T8: =IF(External!D$13>0,External!$E13,External!$E11) -> Medium | U8: =IF('IS Risk Assessment'!E$11>0,'IS Risk Assessment'!$E11,'IS Risk Assessment'!$E9) -> Low | W8: =IF(COUNTIF(Q8:U8,"High")>=1,"High",IF(COUNTIF(Q8:U8,"Medium")>=1,"Medium",IF(COUNTIF(Q8:U8,"Low")>=1,"Low",""))) -> Medium | Y8: Cyber and Information Security protects an organisation's information assets from unauthorised users, disruption, alteration, or destruction, and strengthens the overall control environment to reduce risk. Cyberattacks can lead to direct and indirect impacts that are often significant, as computers, networks, programs, data, and sensitive information are critical components of an organisation. Since organisations rely heavily on information technology resources, having a clearly defined cyber and information security plan, objectives, inherent risks, and effective controls should be a priority for management | AB8: No explicit regulatory requirements | AC8: Developed | AD8: Regarding the Process, it is demonstrated to be mature in the past and this year, too. No significant raised in the past. | AE8: =IF(AND(W8="High",AC8="Strong/Robust"),"Medium",IF(AND(W8="High",AC8="Developed"),"Medium",IF(AND(W8="Medium",AC8="Strong/Robust"),"Low",IF(AND(W8="Medium",AC8="Developed"),"Low",IF(AND(W8="High",AC8="Weak/Undefined"),"High",IF(AND(W8="Medium",AC8="Weak/Undefined"),"Medium","Low")))))) -> Low | AF8: L2 description enhancement | AG8: Possible topics to be covered in audit object AU-109-02-Cyber & IS Strategy and Design (proposed change of scope): Cyber & IS strategy, Resilience Strategy, baseline security configuration & security changes, security in depth, IS assessments regarding threat intelligence/threatlandscape), End user awareness regarding private communication channels such as Whatsapp (e.g. acceptable use policy, social media policy), Social Engineering and targeted personal approach (e.g. spear-fishing, social engineering), use of unapproved and not registered internet services such as miro.com | AH8: >>>>> P_DBAG_CT_9.2_IS Governance >>>>> P_DBAG_SU_11_Info Security 1stLoD (2023) >>>> P_DBAG_CT_9_Information Security 2nd LoD >>>>> P_DBAG_SU_13.6_Technical Security >>>>>> P_DBAG_SU_11.3_Solution Security Mgmt >>>>P_DBAG_SU_11.4_IS Risk Management >>>>P_DBAG_SU_11.1_GS Management & Reporting | AI8: No changes | AV8: Yes | AX8: No | AY8: The process does not have any structured data | AZ8: N/A
D9: AU-109-08-ICT Incident Management | E9: X | F9: X | G9: X | H9: X | I9: X | J9: X | K9: X | L9: X | M9: X | N9: X | O9: X | Q9: =IF('Internal People & Staff'!F$13>0,'Internal People & Staff'!F$13,'Internal People & Staff'!F$11) -> Medium | R9: =IF(Processes!F$12>0,Processes!F$12,Processes!F$10) -> Medium | S9: =IF('Internal Systems'!F$12>0,'Internal Systems'!F$12,'Internal Systems'!F$10) -> Medium | T9: =IF(External!F$13>0,External!F$13,External!F$11) -> Medium | U9: =IF('IS Risk Assessment'!G$11>0,'IS Risk Assessment'!$G11,'IS Risk Assessment'!$G9) -> Low | W9: =IF(COUNTIF(Q9:U9,"High")>=1,"High",IF(COUNTIF(Q9:U9,"Medium")>=1,"Medium",IF(COUNTIF(Q9:U9,"Low")>=1,"Low",""))) -> Medium | Y9: Included possible topics: Information Security incident management incl. Link to crisis management. Based on the IA agile methodology and risk-based approach and in the light of aforementioned information from BCA, IA deemed that there was no risk to be assessed and no test procedures to be carried out in the scope of the 2025-045 Cyber and Information Security audit for this L2. The decision was discussed with the HoIAs at the audit initiation panel. | AB9: No explicit regulatory requirements | AC9: Developed | AD9: As per BCA, L2 was not assessed in Cyber IS audit and current rating is as per the test coverage of this L2 on adhoc basis to check for DORA requiremenbts in the 2025-001 IT Operations Management Audit (AC does not cover the L2). Standard Incident Management process is followed across DBG as observed in the 2025-001 IT Operations Management , L2 controls are the same. These have been shown as mature in the past and this year, too. No significant raised in the past. | AE9: =IF(AND(W9="High",AC9="Strong/Robust"),"Medium",IF(AND(W9="High",AC9="Developed"),"Medium",IF(AND(W9="Medium",AC9="Strong/Robust"),"Low",IF(AND(W9="Medium",AC9="Developed"),"Low",IF(AND(W9="High",AC9="Weak/Undefined"),"High",IF(AND(W9="Medium",AC9="Weak/Undefined"),"Medium","Low")))))) -> Low | AF9: No changes | AG9: N/A | AH9: N/A | AI9: No changes | AV9: Yes | AX9: No | AY9: L2 was not in scope of this audit. The process may have structured data and should be looked into in next regular audit | AZ9: N/A
D10: AU-109-09-Cyber & IS Prevention | E10: X | F10: X | G10: X | H10: X | I10: X | J10: X | K10: X | L10: X | M10: X | N10: X | O10: X | Q10: =IF('Internal People & Staff'!G$13>0,'Internal People & Staff'!G$13,'Internal People & Staff'!G$11) -> Medium | R10: =IF(Processes!G$12>0,Processes!G$12,Processes!G$10) -> High | S10: =IF('Internal Systems'!G$12>0,'Internal Systems'!G$12,'Internal Systems'!G$10) -> Medium | T10: =IF(External!G$13>0,External!G$13,External!G$11) -> High | U10: =IF('IS Risk Assessment'!I$11>0,'IS Risk Assessment'!$I11,'IS Risk Assessment'!$I9) -> Medium | W10: =IF(COUNTIF(Q10:U10,"High")>=1,"High",IF(COUNTIF(Q10:U10,"Medium")>=1,"Medium",IF(COUNTIF(Q10:U10,"Low")>=1,"Low",""))) -> High | Y10: All points grouped in this L2 are critical for DBG and so IR is High. AU-109-09-Cyber & IS Prevention - with possible topics: Cryptography and PKI, Continuous Threat Detection & Response: including TVM and xIPS/xIDS, Nation State Attack (the börse as a function), Supply Chain Attack, Anti-Malware, Ransomware protection, Endpoint protection, Data Leakage prevention (DLP), including prevention, web upload DLP and email DLP, Patch Management (security/ functional), outdated versions/ unsupported systems | AB10: No explicit regulatory requirements | AC10: Weak/undefined | AD10: This L2 includes multiple L3s, and at least some of them had significant remediation efforts underway through 2025 in the DORA and AMELI programs. This audit focused on areas not directly targeted by the AMELI and DORA programs: L3s being - cryptography and key management, continuous threat detection and response, threat-led penetration testing (TLPT), and threat intelligence. IA identified weaknesses observed in vulnerability management procedures, cryptography and key management underscoring the impact of operational guidance on control effectiveness. | AE10: =IF(AND(W10="High",AC10="Strong/Robust"),"Medium",IF(AND(W10="High",AC10="Developed"),"Medium",IF(AND(W10="Medium",AC10="Strong/Robust"),"Low",IF(AND(W10="Medium",AC10="Developed"),"Low",IF(AND(W10="High",AC10="Weak/Undefined"),"High",IF(AND(W10="Medium",AC10="Weak/Undefined"),"Medium","Low")))))) -> High | AF10: L2 description enhancement | AG10: AU-109-09-Cyber & IS Prevention - with possible topics: Cryptography and PKI, Continuous Threat Detection & Response: including TVM and xIPS/xIDS, Nation State Attack (the börse as a function), Supply Chain Attack, Anti-Malware, Ransomware protection, Endpoint protection, Data Leakage prevention (DLP), including prevention, web upload DLP and email DLP, Patch Management (security/ functional), outdated versions/ unsupported systems | AH10: >>>> P_DBAG_SU_11.6_Cyber Protection Management >>>>P_DBAG_SU_11.5_Cyber Defense Management >>>>P_DBAG_SU_11.1_GS Management & Reporting >>>>>>> SP_DBAG_SU_11.6.1022_Security Information and Event Management (SIEM) >>>>>>> SP_DBAG_SU_11.4.1019_Supplier Security Consultancy >>>>>>> SP_DBAG_SU_11.5.6046_Security Event Tracking >>>>>>> SP_DBAG_SU_11.4.4070_Manage Security Risks | AI10: No changes | AK10: X | AL10: X | AM10: X | AN10: X | AO10: X | AP10: X | AQ10: X | AR10: X | AS10: X | AT10: X | AV10: Yes | AX10: Yes | AY10: DA test performed during the audit. | AZ10: VMT & Risk Register (AID430)
D11: AU-109-10-Cyber & IS Detection | E11: X | F11: X | G11: X | H11: X | I11: X | J11: X | K11: X | L11: X | M11: X | N11: X | O11: X | Q11: =IF('Internal People & Staff'!H$13>0,'Internal People & Staff'!H$13,'Internal People & Staff'!H$11) -> Medium | R11: =IF(Processes!H$12>0,Processes!H$12,Processes!H$10) -> High | S11: =IF('Internal Systems'!H$12>0,'Internal Systems'!H$12,'Internal Systems'!H$10) -> Medium | T11: =IF(External!H$13>0,External!H$13,External!H$11) -> High | U11: =IF('IS Risk Assessment'!K$11>0,'IS Risk Assessment'!$K11,'IS Risk Assessment'!$K9) -> Medium | W11: =IF(COUNTIF(Q11:U11,"High")>=1,"High",IF(COUNTIF(Q11:U11,"Medium")>=1,"Medium",IF(COUNTIF(Q11:U11,"Low")>=1,"Low",""))) -> High | Y11: All points grouped in this L2 are critical for DBG and so IR is High. AU-109-10-Cyber & IS Detection - with possible topics: Security event monitoring, security state monitoring, IS Forensics, unsupported versions, PenTest, APT, Cloud Platform & Workload Security, DevSecOps, SOC, CERT, SIEM | AB11: No explicit regulatory requirements | AC11: Weak/undefined | AD11: This L2 includes multiple L3s, and had significant remediation efforts underway through 2025 in the DORA and AMELI programs. | AE11: =IF(AND(W11="High",AC11="Strong/Robust"),"Medium",IF(AND(W11="High",AC11="Developed"),"Medium",IF(AND(W11="Medium",AC11="Strong/Robust"),"Low",IF(AND(W11="Medium",AC11="Developed"),"Low",IF(AND(W11="High",AC11="Weak/Undefined"),"High",IF(AND(W11="Medium",AC11="Weak/Undefined"),"Medium","Low")))))) -> High | AF11: L2 description enhancement | AG11: AU-109-10-Cyber & IS Detection - with possible topics: Security event monitoring, security state monitoring, IS Forensics, PenTest, APT, Cloud Platform & Workload Security, DevSecOps, SOC, CERT, SIEM | AH11: >>>> P_DBAG_SU_11.6_Cyber Protection Management >>>>P_DBAG_SU_11.5_Cyber Defense Management >>>>P_DBAG_SU_11.1_GS Management & Reporting >>>>>>> SP_DBAG_SU_11.6.1022_Security Information and Event Management (SIEM) >>>>>>> SP_DBAG_SU_11.4.1019_Supplier Security Consultancy >>>>>>> SP_DBAG_SU_11.5.6046_Security Event Tracking >>>>>>> SP_DBAG_SU_11.4.4070_Manage Security Risks | AI11: No changes | AV11: Yes | AX11: No | AY11: No DA test could be identified during the audit. | AZ11: N/A
D12: AU-109-11-Cyber & IS Control functions (2LoD) | E12: X | F12: X | G12: X | H12: X | I12: X | J12: X | K12: X | L12: X | M12: X | N12: X | O12: X | Q12: =IF('Internal People & Staff'!I$13>0,'Internal People & Staff'!I$13,'Internal People & Staff'!I$11) -> Medium | R12: =IF(Processes!I$12>0,Processes!I$12,Processes!I$10) -> Medium | S12: =IF('Internal Systems'!I$12>0,'Internal Systems'!I$12,'Internal Systems'!I$10) -> Low | T12: =IF(External!I$13>0,External!I$13,External!I$11) -> Low | U12: =IF('IS Risk Assessment'!M$11>0,'IS Risk Assessment'!$M11,'IS Risk Assessment'!$M9) -> Low | W12: =IF(COUNTIF(Q12:U12,"High")>=1,"High",IF(COUNTIF(Q12:U12,"Medium")>=1,"Medium",IF(COUNTIF(Q12:U12,"Low")>=1,"Low",""))) -> Medium | Y12: As per BCA, no tests were planned for this L2, considering open S3/S2 findings from 2024-063 Technology Governance Audit. | AB12: No explicit regulatory requirements | AC12: Developed | AD12: No tests were planned for this L2, considering open S3/S2 findings from 2024-063 Technology Governance Audit. The CAP milestones supported by recent evidence looks ok to mark as developed. | AE12: =IF(AND(W12="High",AC12="Strong/Robust"),"Medium",IF(AND(W12="High",AC12="Developed"),"Medium",IF(AND(W12="Medium",AC12="Strong/Robust"),"Low",IF(AND(W12="Medium",AC12="Developed"),"Low",IF(AND(W12="High",AC12="Weak/Undefined"),"High",IF(AND(W12="Medium",AC12="Weak/Undefined"),"Medium","Low")))))) -> Low | AF12: L2 description enhancement | AG12: AU-109-11-Cyber & IS Control functions (2LoD) - with possible topics: e.g., 2LoD compliance (LE), CISO, IS assurance | AH12: >>>> P_DBAG_CT_9_Information Security 2nd LoD >>>>P_DBAG_SU_11.2_IS Governance and Compl | AI12: No changes | AV12: Yes | AX12: No | AY12: L2 was not in scope of this audit. The process does not have any structured data | AZ12: N/A
D13: AU-109-12-Threat Intelligence | E13: X | F13: X | G13: X | H13: X | I13: X | J13: X | K13: X | L13: X | M13: X | N13: X | O13: X | Q13: =IF('Internal People & Staff'!J$13>0,'Internal People & Staff'!J$13,'Internal People & Staff'!J$11) -> Medium | R13: =IF(Processes!J$12>0,Processes!J$12,Processes!J$10) -> Medium | S13: =IF('Internal Systems'!J$12>0,'Internal Systems'!J$12,'Internal Systems'!J$10) -> Medium | T13: =IF(External!J$13>0,External!J$13,External!J$11) -> Medium | U13: =IF('IS Risk Assessment'!O$11>0,'IS Risk Assessment'!$O$11,'IS Risk Assessment'!$O$9) -> Medium | W13: =IF(COUNTIF(Q13:U13,"High")>=1,"High",IF(COUNTIF(Q13:U13,"Medium")>=1,"Medium",IF(COUNTIF(Q13:U13,"Low")>=1,"Low",""))) -> Medium | Y13: The process is safeguarding DBG from cyber and geopolitical threats (including Travel Security), thereby ensuring a timely response to incidents and crisis. Responsible for monitoring and comprehending the rapidly changing Cyber and Geopolitical threat landscape. Through a collaborative intelligence approach, they collect, analyse data and provide real-time threat indicators across the organization, with the goal of improving Deutsche Börse’s overall security posture. | AB13: No explicit regulatory requirements | AC13: Developed | AD13: Two low severity findings were identified regarding missing SoD principles for an application and another, missing application in APMS | AE13: =IF(AND(W13="High",AC13="Strong/Robust"),"Medium",IF(AND(W13="High",AC13="Developed"),"Medium",IF(AND(W13="Medium",AC13="Strong/Robust"),"Low",IF(AND(W13="Medium",AC13="Developed"),"Low",IF(AND(W13="High",AC13="Weak/Undefined"),"High",IF(AND(W13="Medium",AC13="Weak/Undefined"),"Medium","Low")))))) -> Low | AF13: L2 description enhancement | AG13: The threat intelligence is gathered on following points: Cyber Threat Intelligence, Geopolitical (including Travel Security), Physical Threat Intelligence (related to office buildings, postal, emergency services, etc.) | AH13: >>>> P_DBAG_SU_11.6_Cyber Protection Management >>>>P_DBAG_SU_11.5_Cyber Defense Management >>>>P_DBAG_SU_11.1_GS Management & Reporting >>>>>>> SP_DBAG_SU_11.6.1022_Security Information and Event Management (SIEM) >>>>>>> SP_DBAG_SU_11.4.1019_Supplier Security Consultancy >>>>>>> SP_DBAG_SU_11.5.6046_Security Event Tracking >>>>>>> SP_DBAG_SU_11.4.4070_Manage Security Risks | AI13: No changes | AK13: X | AU13: X | AV13: Yes | AX13: No | AY13: No DA test could be identified during the audit. | AZ13: N/A
D14: AU-121-04-CSDR Cyber & IS | I14: X | K14: X | L14: X | Q14: =IF('Internal People & Staff'!K$13>0,'Internal People & Staff'!K$13,'Internal People & Staff'!K$11) | R14: =IF(Processes!K$12>0,Processes!K$12,Processes!K$10) | S14: =IF('Internal Systems'!K$12>0,'Internal Systems'!K$12,'Internal Systems'!K$10) | T14: =IF(External!K$13>0,External!K$13,External!K$11) | U14: =IF('IS Risk Assessment'!Q$11>0,'IS Risk Assessment'!$Q$11,'IS Risk Assessment'!$Q$9) | W14: =IF(COUNTIF(Q14:U14,"High")>=1,"High",IF(COUNTIF(Q14:U14,"Medium")>=1,"Medium",IF(COUNTIF(Q14:U14,"Low")>=1,"Low",""))) | Y14: Under CSDR (Central Securities Depositories Regulation), relevant IT L2 (AU-121-04) impacting CSD core services need to be tested once in a year. Applicable only to CBF and CBL legal entities (incl. LuxCSD). The scope of this L2 will have specific focus on Cyber and Information Security activities with attention on Core CSD applications. | AA14: 1Y | AB14: Under CSDR (Central Securities Depositories Regulation), relevant IT L2 (AU-121-04) impacting CSD core services need to be tested once in a year. Applicable only to CBF and CBL legal entities (incl. LuxCSD). The scope of this L2 will have specific focus on Cyber and Information Security activities with attention on Core CSD applications. | AC14: Developed | AD14: To be removed, should not be applicable here | AE14: =IF(AND(W14="High",AC14="Strong/Robust"),"Medium",IF(AND(W14="High",AC14="Developed"),"Medium",IF(AND(W14="Medium",AC14="Strong/Robust"),"Low",IF(AND(W14="Medium",AC14="Developed"),"Low",IF(AND(W14="High",AC14="Weak/Undefined"),"High",IF(AND(W14="Medium",AC14="Weak/Undefined"),"Medium","Low")))))) -> Low | AF14: Should be removed based on IT deputy discussion | AG14: N/A | AH14: All of the above | AI14: No changes | AV14: Yes | AX14: No | AY14: No DA test could be identified during the audit. | AZ14: N/A
Q15: =IF('Internal People & Staff'!L$13>0,'Internal People & Staff'!L$13,'Internal People & Staff'!L$11) | R15: =IF(Processes!L$12>0,Processes!L$12,Processes!L$10) -> Low | S15: =IF('Internal Systems'!L$12>0,'Internal Systems'!L$12,'Internal Systems'!L$10) | T15: =IF(External!L$13>0,External!L$13,External!L$11) | U15: =IF('IS Risk Assessment'!S$11>0,'IS Risk Assessment'!S$11,'IS Risk Assessment'!S$9) | W15: =IF(COUNTIF(Q15:U15,"High")>=1,"High",IF(COUNTIF(Q15:U15,"Medium")>=1,"Medium",IF(COUNTIF(Q15:U15,"Low")>=1,"Low",""))) -> Low | AE15: =IF(AND(W15="High",AC15="Strong/Robust"),"Medium",IF(AND(W15="High",AC15="Developed"),"Medium",IF(AND(W15="Medium",AC15="Strong/Robust"),"Low",IF(AND(W15="Medium",AC15="Developed"),"Low",IF(AND(W15="High",AC15="Weak/Undefined"),"High",IF(AND(W15="Medium",AC15="Weak/Undefined"),"Medium","Low")))))) -> Low
Q16: =IF('Internal People & Staff'!M$13>0,'Internal People & Staff'!M$13,'Internal People & Staff'!M$11) | R16: =IF(Processes!M$12>0,Processes!M$12,Processes!M$10) | S16: =IF('Internal Systems'!M$12>0,'Internal Systems'!M$12,'Internal Systems'!M$10) | T16: =IF(External!M$13>0,External!M$13,External!M$11) | U16: =IF('IS Risk Assessment'!U$11>0,'IS Risk Assessment'!U$11,'IS Risk Assessment'!U$9) | W16: =IF(COUNTIF(Q16:U16,"High")>=1,"High",IF(COUNTIF(Q16:U16,"Medium")>=1,"Medium",IF(COUNTIF(Q16:U16,"Low")>=1,"Low",""))) | AE16: =IF(AND(W16="High",AC16="Strong/Robust"),"Medium",IF(AND(W16="High",AC16="Developed"),"Medium",IF(AND(W16="Medium",AC16="Strong/Robust"),"Low",IF(AND(W16="Medium",AC16="Developed"),"Low",IF(AND(W16="High",AC16="Weak/Undefined"),"High",IF(AND(W16="Medium",AC16="Weak/Undefined"),"Medium","Low")))))) -> Low
Q17: =IF('Internal People & Staff'!N$13>0,'Internal People & Staff'!N$13,'Internal People & Staff'!N$11) | R17: =IF(Processes!N$12>0,Processes!N$12,Processes!N$10) | S17: =IF('Internal Systems'!N$12>0,'Internal Systems'!N$12,'Internal Systems'!N$10) | T17: =IF(External!N$13>0,External!N$13,External!N$11) | U17: =IF('IS Risk Assessment'!W$11>0,'IS Risk Assessment'!W$11,'IS Risk Assessment'!W$9) | W17: =IF(COUNTIF(Q17:U17,"High")>=1,"High",IF(COUNTIF(Q17:U17,"Medium")>=1,"Medium",IF(COUNTIF(Q17:U17,"Low")>=1,"Low",""))) | AE17: =IF(AND(W17="High",AC17="Strong/Robust"),"Medium",IF(AND(W17="High",AC17="Developed"),"Medium",IF(AND(W17="Medium",AC17="Strong/Robust"),"Low",IF(AND(W17="Medium",AC17="Developed"),"Low",IF(AND(W17="High",AC17="Weak/Undefined"),"High",IF(AND(W17="Medium",AC17="Weak/Undefined"),"Medium","Low")))))) -> Low
Q18: =IF('Internal People & Staff'!O$13>0,'Internal People & Staff'!O$13,'Internal People & Staff'!O$11) | R18: =IF(Processes!O$12>0,Processes!O$12,Processes!O$10) | S18: =IF('Internal Systems'!O$12>0,'Internal Systems'!O$12,'Internal Systems'!O$10) | T18: =IF(External!O$13>0,External!O$13,External!O$11) | U18: =IF('IS Risk Assessment'!Y$11>0,'IS Risk Assessment'!Y$11,'IS Risk Assessment'!Y$9) | W18: =IF(COUNTIF(Q18:U18,"High")>=1,"High",IF(COUNTIF(Q18:U18,"Medium")>=1,"Medium",IF(COUNTIF(Q18:U18,"Low")>=1,"Low",""))) | AE18: =IF(AND(W18="High",AC18="Strong/Robust"),"Medium",IF(AND(W18="High",AC18="Developed"),"Medium",IF(AND(W18="Medium",AC18="Strong/Robust"),"Low",IF(AND(W18="Medium",AC18="Developed"),"Low",IF(AND(W18="High",AC18="Weak/Undefined"),"High",IF(AND(W18="Medium",AC18="Weak/Undefined"),"Medium","Low")))))) -> Low
Q19: =IF('Internal People & Staff'!P$13>0,'Internal People & Staff'!P$13,'Internal People & Staff'!P$11) | R19: =IF(Processes!P$12>0,Processes!P$12,Processes!P$10) | S19: =IF('Internal Systems'!P$12>0,'Internal Systems'!P$12,'Internal Systems'!P$10) | T19: =IF(External!P$13>0,External!P$13,External!P$11) | U19: =IF('IS Risk Assessment'!AA$11>0,'IS Risk Assessment'!AA$11,'IS Risk Assessment'!AA$9) | W19: =IF(COUNTIF(Q19:U19,"High")>=1,"High",IF(COUNTIF(Q19:U19,"Medium")>=1,"Medium",IF(COUNTIF(Q19:U19,"Low")>=1,"Low",""))) | AE19: =IF(AND(W19="High",AC19="Strong/Robust"),"Medium",IF(AND(W19="High",AC19="Developed"),"Medium",IF(AND(W19="Medium",AC19="Strong/Robust"),"Low",IF(AND(W19="Medium",AC19="Developed"),"Low",IF(AND(W19="High",AC19="Weak/Undefined"),"High",IF(AND(W19="Medium",AC19="Weak/Undefined"),"Medium","Low")))))) -> Low
Q20: =IF('Internal People & Staff'!Q$13>0,'Internal People & Staff'!Q$13,'Internal People & Staff'!Q$11) | R20: =IF(Processes!Q$12>0,Processes!Q$12,Processes!Q$10) | S20: =IF('Internal Systems'!Q$12>0,'Internal Systems'!Q$12,'Internal Systems'!Q$10) | T20: =IF(External!Q$13>0,External!Q$13,External!Q$11) | U20: =IF('IS Risk Assessment'!AC$11>0,'IS Risk Assessment'!AC$11,'IS Risk Assessment'!AC$9) | W20: =IF(COUNTIF(Q20:U20,"High")>=1,"High",IF(COUNTIF(Q20:U20,"Medium")>=1,"Medium",IF(COUNTIF(Q20:U20,"Low")>=1,"Low",""))) | AE20: =IF(AND(W20="High",AC20="Strong/Robust"),"Medium",IF(AND(W20="High",AC20="Developed"),"Medium",IF(AND(W20="Medium",AC20="Strong/Robust"),"Low",IF(AND(W20="Medium",AC20="Developed"),"Low",IF(AND(W20="High",AC20="Weak/Undefined"),"High",IF(AND(W20="Medium",AC20="Weak/Undefined"),"Medium","Low")))))) -> Low
Q21: =IF('Internal People & Staff'!R$13>0,'Internal People & Staff'!R$13,'Internal People & Staff'!R$11) | R21: =IF(Processes!R$12>0,Processes!R$12,Processes!R$10) | S21: =IF('Internal Systems'!R$12>0,'Internal Systems'!R$12,'Internal Systems'!R$10) | T21: =IF(External!R$13>0,External!R$13,External!R$11) | U21: =IF('IS Risk Assessment'!AE$11>0,'IS Risk Assessment'!AE$11,'IS Risk Assessment'!AE$9) | W21: =IF(COUNTIF(Q21:U21,"High")>=1,"High",IF(COUNTIF(Q21:U21,"Medium")>=1,"Medium",IF(COUNTIF(Q21:U21,"Low")>=1,"Low",""))) | AE21: =IF(AND(W21="High",AC21="Strong/Robust"),"Medium",IF(AND(W21="High",AC21="Developed"),"Medium",IF(AND(W21="Medium",AC21="Strong/Robust"),"Low",IF(AND(W21="Medium",AC21="Developed"),"Low",IF(AND(W21="High",AC21="Weak/Undefined"),"High",IF(AND(W21="Medium",AC21="Weak/Undefined"),"Medium","Low")))))) -> Low
Q22: =IF('Internal People & Staff'!S$13>0,'Internal People & Staff'!S$13,'Internal People & Staff'!S$11) | R22: =IF(Processes!S$12>0,Processes!S$12,Processes!S$10) | S22: =IF('Internal Systems'!S$12>0,'Internal Systems'!S$12,'Internal Systems'!S$10) | T22: =IF(External!S$13>0,External!S$13,External!S$11) | U22: =IF('IS Risk Assessment'!AG$11>0,'IS Risk Assessment'!AG$11,'IS Risk Assessment'!AG$9) | W22: =IF(COUNTIF(Q22:U22,"High")>=1,"High",IF(COUNTIF(Q22:U22,"Medium")>=1,"Medium",IF(COUNTIF(Q22:U22,"Low")>=1,"Low",""))) | AE22: =IF(AND(W22="High",AC22="Strong/Robust"),"Medium",IF(AND(W22="High",AC22="Developed"),"Medium",IF(AND(W22="Medium",AC22="Strong/Robust"),"Low",IF(AND(W22="Medium",AC22="Developed"),"Low",IF(AND(W22="High",AC22="Weak/Undefined"),"High",IF(AND(W22="Medium",AC22="Weak/Undefined"),"Medium","Low")))))) -> Low
Q23: =IF('Internal People & Staff'!T$13>0,'Internal People & Staff'!T$13,'Internal People & Staff'!T$11) | R23: =IF(Processes!T$12>0,Processes!T$12,Processes!T$10) | S23: =IF('Internal Systems'!T$12>0,'Internal Systems'!T$12,'Internal Systems'!T$10) | T23: =IF(External!T$13>0,External!T$13,External!T$11) | U23: =IF('IS Risk Assessment'!AI$11>0,'IS Risk Assessment'!AI$11,'IS Risk Assessment'!AI$9) | W23: =IF(COUNTIF(Q23:U23,"High")>=1,"High",IF(COUNTIF(Q23:U23,"Medium")>=1,"Medium",IF(COUNTIF(Q23:U23,"Low")>=1,"Low",""))) | AE23: =IF(AND(W23="High",AC23="Strong/Robust"),"Medium",IF(AND(W23="High",AC23="Developed"),"Medium",IF(AND(W23="Medium",AC23="Strong/Robust"),"Low",IF(AND(W23="Medium",AC23="Developed"),"Low",IF(AND(W23="High",AC23="Weak/Undefined"),"High",IF(AND(W23="Medium",AC23="Weak/Undefined"),"Medium","Low")))))) -> Low
Q24: =IF('Internal People & Staff'!U$13>0,'Internal People & Staff'!U$13,'Internal People & Staff'!U$11) | R24: =IF(Processes!U$12>0,Processes!U$12,Processes!U$10) | S24: =IF('Internal Systems'!U$12>0,'Internal Systems'!U$12,'Internal Systems'!U$10) | T24: =IF(External!U$13>0,External!U$13,External!U$11) | U24: =IF('IS Risk Assessment'!AK$11>0,'IS Risk Assessment'!AK$11,'IS Risk Assessment'!AK$9) | W24: =IF(COUNTIF(Q24:U24,"High")>=1,"High",IF(COUNTIF(Q24:U24,"Medium")>=1,"Medium",IF(COUNTIF(Q24:U24,"Low")>=1,"Low",""))) | AE24: =IF(AND(W24="High",AC24="Strong/Robust"),"Medium",IF(AND(W24="High",AC24="Developed"),"Medium",IF(AND(W24="Medium",AC24="Strong/Robust"),"Low",IF(AND(W24="Medium",AC24="Developed"),"Low",IF(AND(W24="High",AC24="Weak/Undefined"),"High",IF(AND(W24="Medium",AC24="Weak/Undefined"),"Medium","Low")))))) -> Low
Q25: =IF('Internal People & Staff'!V$13>0,'Internal People & Staff'!V$13,'Internal People & Staff'!V$11) | R25: =IF(Processes!V$12>0,Processes!V$12,Processes!V$10) | S25: =IF('Internal Systems'!V$12>0,'Internal Systems'!V$12,'Internal Systems'!V$10) | T25: =IF(External!V$13>0,External!V$13,External!V$11) | U25: =IF('IS Risk Assessment'!AM$11>0,'IS Risk Assessment'!AM$11,'IS Risk Assessment'!AM$9) | W25: =IF(COUNTIF(Q25:U25,"High")>=1,"High",IF(COUNTIF(Q25:U25,"Medium")>=1,"Medium",IF(COUNTIF(Q25:U25,"Low")>=1,"Low",""))) | AE25: =IF(AND(W25="High",AC25="Strong/Robust"),"Medium",IF(AND(W25="High",AC25="Developed"),"Medium",IF(AND(W25="Medium",AC25="Strong/Robust"),"Low",IF(AND(W25="Medium",AC25="Developed"),"Low",IF(AND(W25="High",AC25="Weak/Undefined"),"High",IF(AND(W25="Medium",AC25="Weak/Undefined"),"Medium","Low")))))) -> Low
Q26: =IF('Internal People & Staff'!W$13>0,'Internal People & Staff'!W$13,'Internal People & Staff'!W$11) | R26: =IF(Processes!W$12>0,Processes!W$12,Processes!W$10) | S26: =IF('Internal Systems'!W$12>0,'Internal Systems'!W$12,'Internal Systems'!W$10) | T26: =IF(External!W$13>0,External!W$13,External!W$11) | U26: =IF('IS Risk Assessment'!AO$11>0,'IS Risk Assessment'!AO$11,'IS Risk Assessment'!AO$9) | W26: =IF(COUNTIF(Q26:U26,"High")>=1,"High",IF(COUNTIF(Q26:U26,"Medium")>=1,"Medium",IF(COUNTIF(Q26:U26,"Low")>=1,"Low",""))) | AE26: =IF(AND(W26="High",AC26="Strong/Robust"),"Medium",IF(AND(W26="High",AC26="Developed"),"Medium",IF(AND(W26="Medium",AC26="Strong/Robust"),"Low",IF(AND(W26="Medium",AC26="Developed"),"Low",IF(AND(W26="High",AC26="Weak/Undefined"),"High",IF(AND(W26="Medium",AC26="Weak/Undefined"),"Medium","Low")))))) -> Low
Q27: =IF('Internal People & Staff'!X$13>0,'Internal People & Staff'!X$13,'Internal People & Staff'!X$11) | R27: =IF(Processes!X$12>0,Processes!X$12,Processes!X$10) | S27: =IF('Internal Systems'!X$12>0,'Internal Systems'!X$12,'Internal Systems'!X$10) | T27: =IF(External!X$13>0,External!X$13,External!X$11) | U27: =IF('IS Risk Assessment'!AQ$11>0,'IS Risk Assessment'!AQ$11,'IS Risk Assessment'!AQ$9) | W27: =IF(COUNTIF(Q27:U27,"High")>=1,"High",IF(COUNTIF(Q27:U27,"Medium")>=1,"Medium",IF(COUNTIF(Q27:U27,"Low")>=1,"Low",""))) | AE27: =IF(AND(W27="High",AC27="Strong/Robust"),"Medium",IF(AND(W27="High",AC27="Developed"),"Medium",IF(AND(W27="Medium",AC27="Strong/Robust"),"Low",IF(AND(W27="Medium",AC27="Developed"),"Low",IF(AND(W27="High",AC27="Weak/Undefined"),"High",IF(AND(W27="Medium",AC27="Weak/Undefined"),"Medium","Low")))))) -> Low
Q28: =IF('Internal People & Staff'!Y$13>0,'Internal People & Staff'!Y$13,'Internal People & Staff'!Y$11) | R28: =IF(Processes!Y$12>0,Processes!Y$12,Processes!Y$10) | S28: =IF('Internal Systems'!Y$12>0,'Internal Systems'!Y$12,'Internal Systems'!Y$10) | T28: =IF(External!Y$13>0,External!Y$13,External!Y$11) | U28: =IF('IS Risk Assessment'!AS$11>0,'IS Risk Assessment'!AS$11,'IS Risk Assessment'!AS$9) | W28: =IF(COUNTIF(Q28:U28,"High")>=1,"High",IF(COUNTIF(Q28:U28,"Medium")>=1,"Medium",IF(COUNTIF(Q28:U28,"Low")>=1,"Low",""))) | AE28: =IF(AND(W28="High",AC28="Strong/Robust"),"Medium",IF(AND(W28="High",AC28="Developed"),"Medium",IF(AND(W28="Medium",AC28="Strong/Robust"),"Low",IF(AND(W28="Medium",AC28="Developed"),"Low",IF(AND(W28="High",AC28="Weak/Undefined"),"High",IF(AND(W28="Medium",AC28="Weak/Undefined"),"Medium","Low")))))) -> Low
Q29: =IF('Internal People & Staff'!Z$13>0,'Internal People & Staff'!Z$13,'Internal People & Staff'!Z$11) | R29: =IF(Processes!Z$12>0,Processes!Z$12,Processes!Z$10) | S29: =IF('Internal Systems'!Z$12>0,'Internal Systems'!Z$12,'Internal Systems'!Z$10) | T29: =IF(External!Z$13>0,External!Z$13,External!Z$11) | U29: =IF('IS Risk Assessment'!AU$11>0,'IS Risk Assessment'!AU$11,'IS Risk Assessment'!AU$9) | W29: =IF(COUNTIF(Q29:U29,"High")>=1,"High",IF(COUNTIF(Q29:U29,"Medium")>=1,"Medium",IF(COUNTIF(Q29:U29,"Low")>=1,"Low",""))) | AE29: =IF(AND(W29="High",AC29="Strong/Robust"),"Medium",IF(AND(W29="High",AC29="Developed"),"Medium",IF(AND(W29="Medium",AC29="Strong/Robust"),"Low",IF(AND(W29="Medium",AC29="Developed"),"Low",IF(AND(W29="High",AC29="Weak/Undefined"),"High",IF(AND(W29="Medium",AC29="Weak/Undefined"),"Medium","Low")))))) -> Low
Q30: =IF('Internal People & Staff'!AA$13>0,'Internal People & Staff'!AA$13,'Internal People & Staff'!AA$11) | R30: =IF(Processes!AA$12>0,Processes!AA$12,Processes!AA$10) | S30: =IF('Internal Systems'!AA$12>0,'Internal Systems'!AA$12,'Internal Systems'!AA$10) | T30: =IF(External!AA$13>0,External!AA$13,External!AA$11) | U30: =IF('IS Risk Assessment'!AW$11>0,'IS Risk Assessment'!AW$11,'IS Risk Assessment'!AW$9) | W30: =IF(COUNTIF(Q30:U30,"High")>=1,"High",IF(COUNTIF(Q30:U30,"Medium")>=1,"Medium",IF(COUNTIF(Q30:U30,"Low")>=1,"Low",""))) | AE30: =IF(AND(W30="High",AC30="Strong/Robust"),"Medium",IF(AND(W30="High",AC30="Developed"),"Medium",IF(AND(W30="Medium",AC30="Strong/Robust"),"Low",IF(AND(W30="Medium",AC30="Developed"),"Low",IF(AND(W30="High",AC30="Weak/Undefined"),"High",IF(AND(W30="Medium",AC30="Weak/Undefined"),"Medium","Low")))))) -> Low
Q31: =IF('Internal People & Staff'!AB$13>0,'Internal People & Staff'!AB$13,'Internal People & Staff'!AB$11) | R31: =IF(Processes!AB$12>0,Processes!AB$12,Processes!AB$10) | S31: =IF('Internal Systems'!AB$12>0,'Internal Systems'!AB$12,'Internal Systems'!AB$10) | T31: =IF(External!AB$13>0,External!AB$13,External!AB$11) | U31: =IF('IS Risk Assessment'!AY$11>0,'IS Risk Assessment'!AY$11,'IS Risk Assessment'!AY$9) | W31: =IF(COUNTIF(Q31:U31,"High")>=1,"High",IF(COUNTIF(Q31:U31,"Medium")>=1,"Medium",IF(COUNTIF(Q31:U31,"Low")>=1,"Low",""))) | AE31: =IF(AND(W31="High",AC31="Strong/Robust"),"Medium",IF(AND(W31="High",AC31="Developed"),"Medium",IF(AND(W31="Medium",AC31="Strong/Robust"),"Low",IF(AND(W31="Medium",AC31="Developed"),"Low",IF(AND(W31="High",AC31="Weak/Undefined"),"High",IF(AND(W31="Medium",AC31="Weak/Undefined"),"Medium","Low")))))) -> Low
Q32: =IF('Internal People & Staff'!AC$13>0,'Internal People & Staff'!AC$13,'Internal People & Staff'!AC$11) | R32: =IF(Processes!AC$12>0,Processes!AC$12,Processes!AC$10) | S32: =IF('Internal Systems'!AC$12>0,'Internal Systems'!AC$12,'Internal Systems'!AC$10) | T32: =IF(External!AC$13>0,External!AC$13,External!AC$11) | U32: =IF('IS Risk Assessment'!BA$11>0,'IS Risk Assessment'!BA$11,'IS Risk Assessment'!BA$9) | W32: =IF(COUNTIF(Q32:U32,"High")>=1,"High",IF(COUNTIF(Q32:U32,"Medium")>=1,"Medium",IF(COUNTIF(Q32:U32,"Low")>=1,"Low",""))) | AE32: =IF(AND(W32="High",AC32="Strong/Robust"),"Medium",IF(AND(W32="High",AC32="Developed"),"Medium",IF(AND(W32="Medium",AC32="Strong/Robust"),"Low",IF(AND(W32="Medium",AC32="Developed"),"Low",IF(AND(W32="High",AC32="Weak/Undefined"),"High",IF(AND(W32="Medium",AC32="Weak/Undefined"),"Medium","Low")))))) -> Low
Q33: =IF('Internal People & Staff'!AD$13>0,'Internal People & Staff'!AD$13,'Internal People & Staff'!AD$11) | R33: =IF(Processes!AD$12>0,Processes!AD$12,Processes!AD$10) | S33: =IF('Internal Systems'!AD$12>0,'Internal Systems'!AD$12,'Internal Systems'!AD$10) | T33: =IF(External!AD$13>0,External!AD$13,External!AD$11) | U33: =IF('IS Risk Assessment'!BC$11>0,'IS Risk Assessment'!BC$11,'IS Risk Assessment'!BC$9) | W33: =IF(COUNTIF(Q33:U33,"High")>=1,"High",IF(COUNTIF(Q33:U33,"Medium")>=1,"Medium",IF(COUNTIF(Q33:U33,"Low")>=1,"Low",""))) | AE33: =IF(AND(W33="High",AC33="Strong/Robust"),"Medium",IF(AND(W33="High",AC33="Developed"),"Medium",IF(AND(W33="Medium",AC33="Strong/Robust"),"Low",IF(AND(W33="Medium",AC33="Developed"),"Low",IF(AND(W33="High",AC33="Weak/Undefined"),"High",IF(AND(W33="Medium",AC33="Weak/Undefined"),"Medium","Low")))))) -> Low
Q34: =IF('Internal People & Staff'!AE$13>0,'Internal People & Staff'!AE$13,'Internal People & Staff'!AE$11) | R34: =IF(Processes!AE$12>0,Processes!AE$12,Processes!AE$10) | S34: =IF('Internal Systems'!AE$12>0,'Internal Systems'!AE$12,'Internal Systems'!AE$10) | T34: =IF(External!AE$13>0,External!AE$13,External!AE$11) | U34: =IF('IS Risk Assessment'!BE$11>0,'IS Risk Assessment'!BE$11,'IS Risk Assessment'!BE$9) | W34: =IF(COUNTIF(Q34:U34,"High")>=1,"High",IF(COUNTIF(Q34:U34,"Medium")>=1,"Medium",IF(COUNTIF(Q34:U34,"Low")>=1,"Low",""))) | AE34: =IF(AND(W34="High",AC34="Strong/Robust"),"Medium",IF(AND(W34="High",AC34="Developed"),"Medium",IF(AND(W34="Medium",AC34="Strong/Robust"),"Low",IF(AND(W34="Medium",AC34="Developed"),"Low",IF(AND(W34="High",AC34="Weak/Undefined"),"High",IF(AND(W34="Medium",AC34="Weak/Undefined"),"Medium","Low")))))) -> Low
Q35: =IF('Internal People & Staff'!AF$13>0,'Internal People & Staff'!AF$13,'Internal People & Staff'!AF$11) | R35: =IF(Processes!AF$12>0,Processes!AF$12,Processes!AF$10) | S35: =IF('Internal Systems'!AF$12>0,'Internal Systems'!AF$12,'Internal Systems'!AF$10) | T35: =IF(External!AF$13>0,External!AF$13,External!AF$11) | U35: =IF('IS Risk Assessment'!BG$11>0,'IS Risk Assessment'!BG$11,'IS Risk Assessment'!BG$9) | W35: =IF(COUNTIF(Q35:U35,"High")>=1,"High",IF(COUNTIF(Q35:U35,"Medium")>=1,"Medium",IF(COUNTIF(Q35:U35,"Low")>=1,"Low",""))) | AE35: =IF(AND(W35="High",AC35="Strong/Robust"),"Medium",IF(AND(W35="High",AC35="Developed"),"Medium",IF(AND(W35="Medium",AC35="Strong/Robust"),"Low",IF(AND(W35="Medium",AC35="Developed"),"Low",IF(AND(W35="High",AC35="Weak/Undefined"),"High",IF(AND(W35="Medium",AC35="Weak/Undefined"),"Medium","Low")))))) -> Low
Q36: =IF('Internal People & Staff'!AG$13>0,'Internal People & Staff'!AG$13,'Internal People & Staff'!AG$11) | R36: =IF(Processes!AG$12>0,Processes!AG$12,Processes!AG$10) | S36: =IF('Internal Systems'!AG$12>0,'Internal Systems'!AG$12,'Internal Systems'!AG$10) | T36: =IF(External!AG$13>0,External!AG$13,External!AG$11) | U36: =IF('IS Risk Assessment'!BI$11>0,'IS Risk Assessment'!BI$11,'IS Risk Assessment'!BI$9) | W36: =IF(COUNTIF(Q36:U36,"High")>=1,"High",IF(COUNTIF(Q36:U36,"Medium")>=1,"Medium",IF(COUNTIF(Q36:U36,"Low")>=1,"Low",""))) | AE36: =IF(AND(W36="High",AC36="Strong/Robust"),"Medium",IF(AND(W36="High",AC36="Developed"),"Medium",IF(AND(W36="Medium",AC36="Strong/Robust"),"Low",IF(AND(W36="Medium",AC36="Developed"),"Low",IF(AND(W36="High",AC36="Weak/Undefined"),"High",IF(AND(W36="Medium",AC36="Weak/Undefined"),"Medium","Low")))))) -> Low
Q37: =IF('Internal People & Staff'!AH$13>0,'Internal People & Staff'!AH$13,'Internal People & Staff'!AH$11) | R37: =IF(Processes!AH$12>0,Processes!AH$12,Processes!AH$10) | S37: =IF('Internal Systems'!AH$12>0,'Internal Systems'!AH$12,'Internal Systems'!AH$10) | T37: =IF(External!AH$13>0,External!AH$13,External!AH$11) | U37: =IF('IS Risk Assessment'!BK$11>0,'IS Risk Assessment'!BK$11,'IS Risk Assessment'!BK$9) | W37: =IF(COUNTIF(Q37:U37,"High")>=1,"High",IF(COUNTIF(Q37:U37,"Medium")>=1,"Medium",IF(COUNTIF(Q37:U37,"Low")>=1,"Low",""))) | AE37: =IF(AND(W37="High",AC37="Strong/Robust"),"Medium",IF(AND(W37="High",AC37="Developed"),"Medium",IF(AND(W37="Medium",AC37="Strong/Robust"),"Low",IF(AND(W37="Medium",AC37="Developed"),"Low",IF(AND(W37="High",AC37="Weak/Undefined"),"High",IF(AND(W37="Medium",AC37="Weak/Undefined"),"Medium","Low")))))) -> Low

Sheet Internal People & Staff
A1: Risk Assessment for Risk Category Internal People & Staff
E2: 1 | F2: =E2+1 -> 2 | G2: =F2+1 -> 3 | H2: =G2+1 -> 4 | I2: =H2+1 -> 5 | J2: =I2+1 -> 6 | K2: =J2+1 -> 7 | L2: =K2+1 -> 8 | M2: =L2+1 -> 9 | ... AH2: =AG2+1 -> 30
B3: Audit No. | C3: ='Audit conclusion'!$D$3 -> 2025-045 Cyber and Information Security | D3: Explanation and Guidance | E3: =INDIRECT("'Audit conclusion'!D"&(E2+ROW('Audit conclusion'!D8)-1)) -> AU-109-02-Cyber & IS Strategy and Design | F3: =INDIRECT("'Audit conclusion'!D"&(F2+ROW('Audit conclusion'!H8)-1)) -> AU-109-08-ICT Incident Management | G3: =INDIRECT("'Audit conclusion'!D"&(G2+ROW('Audit conclusion'!I8)-1)) -> AU-109-09-Cyber & IS Prevention | H3: =INDIRECT("'Audit conclusion'!D"&(H2+ROW('Audit conclusion'!J8)-1)) -> AU-109-10-Cyber & IS Detection | I3: =INDIRECT("'Audit conclusion'!D"&(I2+ROW('Audit conclusion'!K8)-1)) -> AU-109-11-Cyber & IS Control functions (2LoD) | J3: =INDIRECT("'Audit conclusion'!D"&(J2+ROW('Audit conclusion'!L8)-1)) -> AU-109-12-Threat Intelligence | K3: =INDIRECT("'Audit conclusion'!D"&(K2+ROW('Audit conclusion'!M8)-1)) -> AU-121-04-CSDR Cyber & IS | L3: =INDIRECT("'Audit conclusion'!D"&(L2+ROW('Audit conclusion'!Y8)-1)) -> 0 | M3: =INDIRECT("'Audit conclusion'!D"&(M2+ROW('Audit conclusion'!AB8)-1)) -> 0 | N3: =INDIRECT("'Audit conclusion'!D"&(N2+ROW('Audit conclusion'!AD8)-1)) -> 0 | O3: =INDIRECT("'Audit conclusion'!D"&(O2+ROW('Audit conclusion'!AG8)-1)) -> 0 | P3: =INDIRECT("'Audit conclusion'!D"&(P2+ROW('Audit conclusion'!AI8)-1)) -> 0 | Q3: =INDIRECT("'Audit conclusion'!D"&(Q2+ROW('Audit conclusion'!AK8)-1)) -> 0 | R3: =INDIRECT("'Audit conclusion'!D"&(R2+ROW('Audit conclusion'!AM8)-1)) -> 0 | S3: =INDIRECT("'Audit conclusion'!D"&(S2+ROW('Audit conclusion'!AU8)-1)) -> 0 | T3: =INDIRECT("'Audit conclusion'!D"&(T2+ROW('Audit conclusion'!AX8)-1)) -> 0 | U3: =INDIRECT("'Audit conclusion'!D"&(U2+ROW('Audit conclusion'!AZ8)-1)) -> 0 | V3: =INDIRECT("'Audit conclusion'!D"&(V2+ROW('Audit conclusion'!BB8)-1)) -> 0 | W3: =INDIRECT("'Audit conclusion'!D"&(W2+ROW('Audit conclusion'!BD8)-1)) -> 0 | X3: =INDIRECT("'Audit conclusion'!D"&(X2+ROW('Audit conclusion'!BF8)-1)) -> 0 | Y3: =INDIRECT("'Audit conclusion'!D"&(Y2+ROW('Audit conclusion'!BH8)-1)) -> 0 | Z3: =INDIRECT("'Audit conclusion'!D"&(Z2+ROW('Audit conclusion'!BJ8)-1)) -> 0 | AA3: =INDIRECT("'Audit conclusion'!D"&(AA2+ROW('Audit conclusion'!BL8)-1)) -> 0 | AB3: =INDIRECT("'Audit conclusion'!D"&(AB2+ROW('Audit conclusion'!BN8)-1)) -> 0 | AC3: =INDIRECT("'Audit conclusion'!D"&(AC2+ROW('Audit conclusion'!BP8)-1)) -> 0 | AD3: =INDIRECT("'Audit conclusion'!D"&(AD2+ROW('Audit conclusion'!BR8)-1)) -> 0 | AE3: =INDIRECT("'Audit conclusion'!D"&(AE2+ROW('Audit conclusion'!BT8)-1)) -> 0 | AF3: =INDIRECT("'Audit conclusion'!D"&(AF2+ROW('Audit conclusion'!BV8)-1)) -> 0 | AG3: =INDIRECT("'Audit conclusion'!D"&(AG2+ROW('Audit conclusion'!BX8)-1)) -> 0 | AH3: =INDIRECT("'Audit conclusion'!D"&(AH2+ROW('Audit conclusion'!BZ8)-1)) -> 0
A4: Criteria for inherent risk | E4: Score | F4: Score | G4: Score | H4: Score | I4: Score | J4: Score | K4: Score | L4: Score | M4: Score | N4: Score | O4: Score | P4: Score | Q4: Score | R4: Score | S4: Score | T4: Score | U4: Score | V4: Score | W4: Score | X4: Score | Y4: Score | Z4: Score | AA4: Score | AB4: Score | AC4: Score | AD4: Score | AE4: Score | AF4: Score | AG4: Score | AH4: Score
A5: 1 | B5: Internal Fraud incentives | C5: High - Regular exposure to sensitive data and (financial) transactions Medium - Occasional exposure to sensitive data and transactions Low - Negligible exposure N/A is not used for this criteria | D5: Audited area performs daily payments transactions or has access to sensitive data with the possibility of involved employees to enrich themselves, spread confidential information or falsify transactions. | E5: 1 | F5: 1 | G5: 3 | H5: 3 | I5: 1 | J5: 2 | K5: n/a
A6: 2 | B6: Required level of qualification | C6: High - highly specialized skillset needed to execute the process; low availability on the market; difficult replacement process with high recruiting costs involved Medium - sufficient availability on the job market of personnel with required background/qualification; advanced training on the job needed to fulfill tasks Low - no specialized skillset needed, easily trained on the job, easy replacement of certain position possible N/A is not used for this criteria | D6: If the execution of the process requires a high qualification this could lead to understaffing. | E6: 3 | F6: 3 | G6: 3 | H6: 3 | I6: 2 | J6: 2 | K6: n/a
A7: 3 | B7: Human error potential | C7: High - Significant share is conducted manually (e.g. > 50% of transaction volume/process steps) Medium - Major share is conducted manually (e.g. 50 % - 26 % transaction volume/process steps) Low - Minor share is conducted manually (e.g. < 26 % transaction volume/process steps) N/A is not used for this criteria | D7: Share of manually driven process steps is an indicator of error proneness. | E7: 2 | F7: 3 | G7: 2 | H7: 2 | I7: 1 | J7: 1 | K7: n/a
A8: 4 | B8: Attrition/turnover rate (in last year) | C8: High - Significant part or subject matter experts left the area; more than 20 % Medium - minor cases of staff turnover; up to 20% Low - Few fluctuation; up to 10% N/A is not used for this criteria | D8: A high fluctuation is an indicator that adequate execution of the process could be at risk. | E8: 1 | F8: 1 | G8: 1 | H8: 1 | I8: 1 | J8: 1 | K8: n/a
A9: 5 | B9: Staffing | C9: High - Key position (process operator) not staffed; more than 20 % of positions open Medium - Team is understaffed; up to 20% of positions open Low - Minor deficits in open positions; up to 10% of positions open N/A is not used for this criteria | D9: A high number of vacant posts in relation to the team size is an indicator that adequate execution of the process could be at risk. | E9: 1 | F9: 1 | G9: 1 | H9: 1 | I9: 1 | J9: 1 | K9: n/a
C10: Average | E10: =IFERROR(IF(COUNTBLANK(E5:E9)>0,"",SUM(E5:E9)/COUNTIF(E5:E9,">=0")),"") -> 1.6 | F10: =IFERROR(IF(COUNTBLANK(F5:F9)>0,"",SUM(F5:F9)/COUNTIF(F5:F9,">=0")),"") -> 1.8 | G10: =IFERROR(IF(COUNTBLANK(G5:G9)>0,"",SUM(G5:G9)/COUNTIF(G5:G9,">=0")),"") -> 2 | H10: =IFERROR(IF(COUNTBLANK(H5:H9)>0,"",SUM(H5:H9)/COUNTIF(H5:H9,">=0")),"") -> 2 | I10: =IFERROR(IF(COUNTBLANK(I5:I9)>0,"",SUM(I5:I9)/COUNTIF(I5:I9,">=0")),"") -> 1.2 | J10: =IFERROR(IF(COUNTBLANK(J5:J9)>0,"",SUM(J5:J9)/COUNTIF(J5:J9,">=0")),"") -> 1.4 | K10: =IFERROR(IF(COUNTBLANK(K5:K9)>0,"",SUM(K5:K9)/COUNTIF(K5:K9,">=0")),"") | L10: =IFERROR(IF(COUNTBLANK(L5:L9)>0,"",SUM(L5:L9)/COUNTIF(L5:L9,">=0")),"") | ... AH10: =IFERROR(IF(COUNTBLANK(AH5:AH9)>0,"",SUM(AH5:AH9)/COUNTIF(AH5:AH9,">=0")),"")
C11: Calculated result to be overridden if deemed not adequate | E11: =IF(E10="","",IF(E10<1.4,"Low",(IF(AND(E10>=1.4,E10<2.4),"Medium",(IF((AND(E10>=2.4)),"High")))))) -> Medium | F11: =IF(F10="","",IF(F10<1.4,"Low",(IF(AND(F10>=1.4,F10<2.4),"Medium",(IF((AND(F10>=2.4)),"High")))))) -> Medium | G11: =IF(G10="","",IF(G10<1.4,"Low",(IF(AND(G10>=1.4,G10<2.4),"Medium",(IF((AND(G10>=2.4)),"High")))))) -> Medium | H11: =IF(H10="","",IF(H10<1.4,"Low",(IF(AND(H10>=1.4,H10<2.4),"Medium",(IF((AND(H10>=2.4)),"High")))))) -> Medium | I11: =IF(I10="","",IF(I10<1.4,"Low",(IF(AND(I10>=1.4,I10<2.4),"Medium",(IF((AND(I10>=2.4)),"High")))))) -> Low | J11: =IF(J10="","",IF(J10<1.4,"Low",(IF(AND(J10>=1.4,J10<2.4),"Medium",(IF((AND(J10>=2.4)),"High")))))) -> Medium | K11: =IF(K10="","",IF(K10<1.4,"Low",(IF(AND(K10>=1.4,K10<2.4),"Medium",(IF((AND(K10>=2.4)),"High")))))) | L11: =IF(L10="","",IF(L10<1.4,"Low",(IF(AND(L10>=1.4,L10<2.4),"Medium",(IF((AND(L10>=2.4)),"High")))))) | ... AH11: =IF(AH10="","",IF(AH10<1.4,"Low",(IF(AND(AH10>=1.4,AH10<2.4),"Medium",(IF((AND(AH10>=2.4)),"High"))))))
C13: Override the result / justification | I13: Medium
D14: Provide justification in case of the override | F14: =IF(F13>0,"Add justification","") | G14: =IF(G13>0,"Add justification","") | H14: =IF(H13>0,"Add justification","") | I14: As per BCA, L2 was not assessed in current audit. No previous assessment was available. IA assessment rating is supported by open S3/S2 findings/CAP from 2024-063 Technology Governance | J14: =IF(J13>0,"Add justification","") | L14: =IF(L13>0,"Add justification","") | M14: =IF(M13>0,"Add justification","") | N14: =IF(N13>0,"Add justification","") | O14: =IF(O13>0,"Add justification","") | P14: =IF(P13>0,"Add justification","") | Q14: =IF(Q13>0,"Add justification","") | R14: =IF(R13>0,"Add justification","") | S14: =IF(S13>0,"Add justification","") | ... AH14: =IF(AH13>0,"Add justification","")
C15: Result of the last risk assessment (Low, Medium, High) | E15: Medium | F15: Medium | G15: Medium | H15: Medium
D16: Provide justification if the risk assessment result changed compared to the previous risk assessment | E16: No change | F16: As per BCA, L2 was not assessed in Cyber IS audit and current rating is from 2025-001 IT Operations Management Audit. Standard Incident Management process is followed across DBG as observed in the 2025-001 IT Operations Management, L2 controls are the same. These have been shown as mature in the past and this year, too | G16: No change | H16: No change | J16: Not assessed in previous audit as separate L2 - current assessment rated as Low

Sheet Sheet1
A1: =IF('Internal People & Staff'!E$13="",'Internal People & Staff'!E$11,IF(OR('Internal People & Staff'!#REF!="Put here justification for overriding",'Internal People & Staff'!#REF!=""),"Put justification for overriding!",'Internal People & Staff'!E$13)) -> Medium | B1: =IF('Internal People & Staff'!F$13="",'Internal People & Staff'!F$11,IF(OR('Internal People & Staff'!#REF!="Put here justification for overriding",'Internal People & Staff'!#REF!=""),"Put justification for overriding!",'Internal People & Staff'!F$13)) -> Medium | C1: =IF('Internal People & Staff'!G$13="",'Internal People & Staff'!G$11,IF(OR('Internal People & Staff'!#REF!="Put here justification for overriding",'Internal People & Staff'!#REF!=""),"Put justification for overriding!",'Internal People & Staff'!G$13)) -> Medium | D1: =IF('Internal People & Staff'!H$13="",'Internal People & Staff'!H$11,IF(OR('Internal People & Staff'!#REF!="Put here justification for overriding",'Internal People & Staff'!#REF!=""),"Put justification for overriding!",'Internal People & Staff'!H$13)) -> Medium | E1: =IF('Internal People & Staff'!I$13="",'Internal People & Staff'!I$11,IF(OR('Internal People & Staff'!#REF!="Put here justification for overriding",'Internal People & Staff'!#REF!=""),"Put justification for overriding!",'Internal People & Staff'!I$13)) -> #REF! | F1: =IF('Internal People & Staff'!J$13="",'Internal People & Staff'!J$11,IF(OR('Internal People & Staff'!#REF!="Put here justification for overriding",'Internal People & Staff'!#REF!=""),"Put justification for overriding!",'Internal People & Staff'!J$13)) -> Medium | G1: =IF('Internal People & Staff'!K$13="",'Internal People & Staff'!K$11,IF(OR('Internal People & Staff'!#REF!="Put here justification for overriding",'Internal People & Staff'!#REF!=""),"Put justification for overriding!",'Internal People & Staff'!K$13)) | H1: =IF('Internal People & Staff'!L$13="",'Internal People & Staff'!L$11,IF(OR('Internal People & Staff'!#REF!="Put here justification for overriding",'Internal People & Staff'!#REF!=""),"Put justification for overriding!",'Internal People & Staff'!L$13)) | ... AD1: =IF('Internal People & Staff'!AH$13="",'Internal People & Staff'!AH$11,IF(OR('Internal People & Staff'!#REF!="Put here justification for overriding",'Internal People & Staff'!#REF!=""),"Put justification for overriding!",'Internal People & Staff'!AH$13))
A2: =IF(Processes!E$12="",Processes!E$10,IF(OR(Processes!#REF!="Put here justification for overriding",Processes!#REF!=""),"Put justification for overriding!",Processes!E$12)) -> Medium | B2: =IF(Processes!F$12="",Processes!F$10,IF(OR(Processes!#REF!="Put here justification for overriding",Processes!#REF!=""),"Put justification for overriding!",Processes!F$12)) -> #REF! | C2: =IF(Processes!G$12="",Processes!G$10,IF(OR(Processes!#REF!="Put here justification for overriding",Processes!#REF!=""),"Put justification for overriding!",Processes!G$12)) -> High | D2: =IF(Processes!H$12="",Processes!H$10,IF(OR(Processes!#REF!="Put here justification for overriding",Processes!#REF!=""),"Put justification for overriding!",Processes!H$12)) -> High | E2: =IF(Processes!I$12="",Processes!I$10,IF(OR(Processes!#REF!="Put here justification for overriding",Processes!#REF!=""),"Put justification for overriding!",Processes!I$12)) -> Medium | F2: =IF(Processes!J$12="",Processes!J$10,IF(OR(Processes!#REF!="Put here justification for overriding",Processes!#REF!=""),"Put justification for overriding!",Processes!J$12)) -> Medium | G2: =IF(Processes!K$12="",Processes!K$10,IF(OR(Processes!#REF!="Put here justification for overriding",Processes!#REF!=""),"Put justification for overriding!",Processes!K$12)) | H2: =IF(Processes!L$12="",Processes!L$10,IF(OR(Processes!#REF!="Put here justification for overriding",Processes!#REF!=""),"Put justification for overriding!",Processes!L$12)) -> #REF! | ... AD2: =IF(Processes!AH$12="",Processes!AH$10,IF(OR(Processes!#REF!="Put here justification for overriding",Processes!#REF!=""),"Put justification for overriding!",Processes!AH$12))
A3: =IF('Internal Systems'!E$12="",'Internal Systems'!E$10,IF(OR('Internal Systems'!#REF!="Put here justification for overriding",'Internal Systems'!#REF!=""),"Put justification for overriding!",'Internal Systems'!E$12)) -> Low | B3: =IF('Internal Systems'!F$12="",'Internal Systems'!F$10,IF(OR('Internal Systems'!#REF!="Put here justification for overriding",'Internal Systems'!#REF!=""),"Put justification for overriding!",'Internal Systems'!F$12)) -> Medium | C3: =IF('Internal Systems'!G$12="",'Internal Systems'!G$10,IF(OR('Internal Systems'!#REF!="Put here justification for overriding",'Internal Systems'!#REF!=""),"Put justification for overriding!",'Internal Systems'!G$12)) -> Medium | D3: =IF('Internal Systems'!H$12="",'Internal Systems'!H$10,IF(OR('Internal Systems'!#REF!="Put here justification for overriding",'Internal Systems'!#REF!=""),"Put justification for overriding!",'Internal Systems'!H$12)) -> Medium | E3: =IF('Internal Systems'!I$12="",'Internal Systems'!I$10,IF(OR('Internal Systems'!#REF!="Put here justification for overriding",'Internal Systems'!#REF!=""),"Put justification for overriding!",'Internal Systems'!I$12)) -> Low | F3: =IF('Internal Systems'!J$12="",'Internal Systems'!J$10,IF(OR('Internal Systems'!#REF!="Put here justification for overriding",'Internal Systems'!#REF!=""),"Put justification for overriding!",'Internal Systems'!J$12)) -> Medium | G3: =IF('Internal Systems'!K$12="",'Internal Systems'!K$10,IF(OR('Internal Systems'!#REF!="Put here justification for overriding",'Internal Systems'!#REF!=""),"Put justification for overriding!",'Internal Systems'!K$12)) | H3: =IF('Internal Systems'!L$12="",'Internal Systems'!L$10,IF(OR('Internal Systems'!#REF!="Put here justification for overriding",'Internal Systems'!#REF!=""),"Put justification for overriding!",'Internal Systems'!L$12)) | ... AC3: =IF('Internal Systems'!AG$12="",'Internal Systems'!AG$10,IF(OR('Internal Systems'!#REF!="Put here justification for overriding",'Internal Systems'!#REF!=""),"Put justification for overriding!",'Internal Systems'!AG$12)) | AD3: =IF('Internal Systems'!AH$12="",'Internal Systems'!AH$10,IF(OR('Internal Systems'!AI$12="Put here justification for overriding",'Internal Systems'!AI$12=""),"Put justification for overriding!",'Internal Systems'!AH$12))
A4: =IF(External!E$13="",External!E$11,IF(OR(External!#REF!="Put here justification for overriding",External!#REF!=""),"Put justification for overriding!",External!E$13)) -> Medium | B4: =IF(External!F$13="",External!F$11,IF(OR(External!#REF!="Put here justification for overriding",External!#REF!=""),"Put justification for overriding!",External!F$13)) -> Medium | C4: =IF(External!G$13="",External!G$11,IF(OR(External!#REF!="Put here justification for overriding",External!#REF!=""),"Put justification for overriding!",External!G$13)) -> High | D4: =IF(External!H$13="",External!H$11,IF(OR(External!#REF!="Put here justification for overriding",External!#REF!=""),"Put justification for overriding!",External!H$13)) -> High | E4: =IF(External!I$13="",External!I$11,IF(OR(External!#REF!="Put here justification for overriding",External!#REF!=""),"Put justification for overriding!",External!I$13)) -> Low | F4: =IF(External!J$13="",External!J$11,IF(OR(External!#REF!="Put here justification for overriding",External!#REF!=""),"Put justification for overriding!",External!J$13)) -> Medium | G4: =IF(External!K$13="",External!K$11,IF(OR(External!#REF!="Put here justification for overriding",External!#REF!=""),"Put justification for overriding!",External!K$13)) | H4: =IF(External!L$13="",External!L$11,IF(OR(External!#REF!="Put here justification for overriding",External!#REF!=""),"Put justification for overriding!",External!L$13)) | ... AD4: =IF(External!AH$13="",External!AH$11,IF(OR(External!#REF!="Put here justification for overriding",External!#REF!=""),"Put justification for overriding!",External!AH$13))
A6: =IF('Internal People & Staff'!$E$13="",'Internal People & Staff'!$E$11,IF(OR('Internal People & Staff'!#REF!="Put here justification for overriding",'Internal People & Staff'!#REF!=""),"Put justification for overriding!",'Internal People & Staff'!$E$13)) -> Medium | B6: =IF(Processes!E$12="",Processes!E$10,IF(OR(Processes!#REF!="Put here justification for overriding",Processes!#REF!=""),"Put justification for overriding!",Processes!E$12)) -> Medium | C6: =IF('Internal Systems'!E$12="",'Internal Systems'!E$10,IF(OR('Internal Systems'!#REF!="Put here justification for overriding",'Internal Systems'!#REF!=""),"Put justification for overriding!",'Internal Systems'!E$12)) -> Low | D6: =IF(External!E$13="",External!E$11,IF(OR(External!#REF!="Put here justification for overriding",External!#REF!=""),"Put justification for overriding!",External!E$13)) -> Medium
A7: =IF('Internal People & Staff'!$F$13="",'Internal People & Staff'!$F$11,IF(OR('Internal People & Staff'!#REF!="Put here justification for overriding",'Internal People & Staff'!#REF!=""),"Put justification for overriding!",'Internal People & Staff'!$F$13)) -> Medium | B7: =IF(Processes!F$12="",Processes!F$10,IF(OR(Processes!#REF!="Put here justification for overriding",Processes!#REF!=""),"Put justification for overriding!",Processes!F$12)) -> #REF! | C7: =IF('Internal Systems'!F$12="",'Internal Systems'!F$10,IF(OR('Internal Systems'!#REF!="Put here justification for overriding",'Internal Systems'!#REF!=""),"Put justification for overriding!",'Internal Systems'!F$12)) -> Medium | D7: =IF(External!F$13="",External!F$11,IF(OR(External!#REF!="Put here justification for overriding",External!#REF!=""),"Put justification for overriding!",External!F$13)) -> Medium
A8: =IF('Internal People & Staff'!$G$13="",'Internal People & Staff'!$G$11,IF(OR('Internal People & Staff'!#REF!="Put here justification for overriding",'Internal People & Staff'!#REF!=""),"Put justification for overriding!",'Internal People & Staff'!$G$13)) -> Medium | B8: =IF(Processes!G$12="",Processes!G$10,IF(OR(Processes!#REF!="Put here justification for overriding",Processes!#REF!=""),"Put justification for overriding!",Processes!G$12)) -> High | C8: =IF('Internal Systems'!G$12="",'Internal Systems'!G$10,IF(OR('Internal Systems'!#REF!="Put here justification for overriding",'Internal Systems'!#REF!=""),"Put justification for overriding!",'Internal Systems'!G$12)) -> Medium | D8: =IF(External!G$13="",External!G$11,IF(OR(External!#REF!="Put here justification for overriding",External!#REF!=""),"Put justification for overriding!",External!G$13)) -> High
A9: =IF('Internal People & Staff'!$H$13="",'Internal People & Staff'!$H$11,IF(OR('Internal People & Staff'!#REF!="Put here justification for overriding",'Internal People & Staff'!#REF!=""),"Put justification for overriding!",'Internal People & Staff'!$H$13)) -> Medium | B9: =IF(Processes!H$12="",Processes!H$10,IF(OR(Processes!#REF!="Put here justification for overriding",Processes!#REF!=""),"Put justification for overriding!",Processes!H$12)) -> High | C9: =IF('Internal Systems'!H$12="",'Internal Systems'!H$10,IF(OR('Internal Systems'!#REF!="Put here justification for overriding",'Internal Systems'!#REF!=""),"Put justification for overriding!",'Internal Systems'!H$12)) -> Medium | D9: =IF(External!H$13="",External!H$11,IF(OR(External!#REF!="Put here justification for overriding",External!#REF!=""),"Put justification for overriding!",External!H$13)) -> High
A10: =IF('Internal People & Staff'!$I$13="",'Internal People & Staff'!$I$11,IF(OR('Internal People & Staff'!#REF!="Put here justification for overriding",'Internal People & Staff'!#REF!=""),"Put justification for overriding!",'Internal People & Staff'!$I$13)) -> #REF! | B10: =IF(Processes!I$12="",Processes!I$10,IF(OR(Processes!#REF!="Put here justification for overriding",Processes!#REF!=""),"Put justification for overriding!",Processes!I$12)) -> Medium | C10: =IF('Internal Systems'!I$12="",'Internal Systems'!I$10,IF(OR('Internal Systems'!#REF!="Put here justification for overriding",'Internal Systems'!#REF!=""),"Put justification for overriding!",'Internal Systems'!I$12)) -> Low | D10: =IF(External!I$13="",External!I$11,IF(OR(External!#REF!="Put here justification for overriding",External!#REF!=""),"Put justification for overriding!",External!I$13)) -> Low
A11: =IF('Internal People & Staff'!J$13="",'Internal People & Staff'!J$11,IF(OR('Internal People & Staff'!#REF!="Put here justification for overriding",'Internal People & Staff'!#REF!=""),"Put justification for overriding!",'Internal People & Staff'!J$13)) -> Medium | B11: =IF(Processes!J$12="",Processes!J$10,IF(OR(Processes!#REF!="Put here justification for overriding",Processes!#REF!=""),"Put justification for overriding!",Processes!J$12)) -> Medium | C11: =IF('Internal Systems'!J$12="",'Internal Systems'!J$10,IF(OR('Internal Systems'!#REF!="Put here justification for overriding",'Internal Systems'!#REF!=""),"Put justification for overriding!",'Internal Systems'!J$12)) -> Medium | D11: =IF(External!J$13="",External!J$11,IF(OR(External!#REF!="Put here justification for overriding",External!#REF!=""),"Put justification for overriding!",External!J$13)) -> Medium
A12: =IF('Internal People & Staff'!K$13="",'Internal People & Staff'!K$11,IF(OR('Internal People & Staff'!#REF!="Put here justification for overriding",'Internal People & Staff'!#REF!=""),"Put justification for overriding!",'Internal People & Staff'!K$13)) | B12: =IF(Processes!K$12="",Processes!K$10,IF(OR(Processes!#REF!="Put here justification for overriding",Processes!#REF!=""),"Put justification for overriding!",Processes!K$12)) | C12: =IF('Internal Systems'!K$12="",'Internal Systems'!K$10,IF(OR('Internal Systems'!#REF!="Put here justification for overriding",'Internal Systems'!#REF!=""),"Put justification for overriding!",'Internal Systems'!K$12)) | D12: =IF(External!K$13="",External!K$11,IF(OR(External!#REF!="Put here justification for overriding",External!#REF!=""),"Put justification for overriding!",External!K$13))
A13: =IF('Internal People & Staff'!L$13="",'Internal People & Staff'!L$11,IF(OR('Internal People & Staff'!#REF!="Put here justification for overriding",'Internal People & Staff'!#REF!=""),"Put justification for overriding!",'Internal People & Staff'!L$13)) | B13: =IF(Processes!L$12="",Processes!L$10,IF(OR(Processes!#REF!="Put here justification for overriding",Processes!#REF!=""),"Put justification for overriding!",Processes!L$12)) -> #REF! | C13: =IF('Internal Systems'!L$12="",'Internal Systems'!L$10,IF(OR('Internal Systems'!#REF!="Put here justification for overriding",'Internal Systems'!#REF!=""),"Put justification for overriding!",'Internal Systems'!L$12)) | D13: =IF(External!L$13="",External!L$11,IF(OR(External!#REF!="Put here justification for overriding",External!#REF!=""),"Put justification for overriding!",External!L$13))
A14: =IF('Internal People & Staff'!M$13="",'Internal People & Staff'!M$11,IF(OR('Internal People & Staff'!#REF!="Put here justification for overriding",'Internal People & Staff'!#REF!=""),"Put justification for overriding!",'Internal People & Staff'!M$13)) | B14: =IF(Processes!M$12="",Processes!M$10,IF(OR(Processes!#REF!="Put here justification for overriding",Processes!#REF!=""),"Put justification for overriding!",Processes!M$12)) | C14: =IF('Internal Systems'!M$12="",'Internal Systems'!M$10,IF(OR('Internal Systems'!#REF!="Put here justification for overriding",'Internal Systems'!#REF!=""),"Put justification for overriding!",'Internal Systems'!M$12)) | D14: =IF(External!M$13="",External!M$11,IF(OR(External!#REF!="Put here justification for overriding",External!#REF!=""),"Put justification for overriding!",External!M$13))
A15: =IF('Internal People & Staff'!N$13="",'Internal People & Staff'!N$11,IF(OR('Internal People & Staff'!#REF!="Put here justification for overriding",'Internal People & Staff'!#REF!=""),"Put justification for overriding!",'Internal People & Staff'!N$13)) | B15: =IF(Processes!N$12="",Processes!N$10,IF(OR(Processes!#REF!="Put here justification for overriding",Processes!#REF!=""),"Put justification for overriding!",Processes!N$12)) | C15: =IF('Internal Systems'!N$12="",'Internal Systems'!N$10,IF(OR('Internal Systems'!#REF!="Put here justification for overriding",'Internal Systems'!#REF!=""),"Put justification for overriding!",'Internal Systems'!N$12)) | D15: =IF(External!N$13="",External!N$11,IF(OR(External!#REF!="Put here justification for overriding",External!#REF!=""),"Put justification for overriding!",External!N$13))
A16: =IF('Internal People & Staff'!O$13="",'Internal People & Staff'!O$11,IF(OR('Internal People & Staff'!#REF!="Put here justification for overriding",'Internal People & Staff'!#REF!=""),"Put justification for overriding!",'Internal People & Staff'!O$13)) | B16: =IF(Processes!O$12="",Processes!O$10,IF(OR(Processes!#REF!="Put here justification for overriding",Processes!#REF!=""),"Put justification for overriding!",Processes!O$12)) | C16: =IF('Internal Systems'!O$12="",'Internal Systems'!O$10,IF(OR('Internal Systems'!#REF!="Put here justification for overriding",'Internal Systems'!#REF!=""),"Put justification for overriding!",'Internal Systems'!O$12)) | D16: =IF(External!O$13="",External!O$11,IF(OR(External!#REF!="Put here justification for overriding",External!#REF!=""),"Put justification for overriding!",External!O$13))
A17: =IF('Internal People & Staff'!P$13="",'Internal People & Staff'!P$11,IF(OR('Internal People & Staff'!#REF!="Put here justification for overriding",'Internal People & Staff'!#REF!=""),"Put justification for overriding!",'Internal People & Staff'!P$13)) | B17: =IF(Processes!P$12="",Processes!P$10,IF(OR(Processes!#REF!="Put here justification for overriding",Processes!#REF!=""),"Put justification for overriding!",Processes!P$12)) | C17: =IF('Internal Systems'!P$12="",'Internal Systems'!P$10,IF(OR('Internal Systems'!#REF!="Put here justification for overriding",'Internal Systems'!#REF!=""),"Put justification for overriding!",'Internal Systems'!P$12)) | D17: =IF(External!P$13="",External!P$11,IF(OR(External!#REF!="Put here justification for overriding",External!#REF!=""),"Put justification for overriding!",External!P$13))
A18: =IF('Internal People & Staff'!Q$13="",'Internal People & Staff'!Q$11,IF(OR('Internal People & Staff'!#REF!="Put here justification for overriding",'Internal People & Staff'!#REF!=""),"Put justification for overriding!",'Internal People & Staff'!Q$13)) | B18: =IF(Processes!Q$12="",Processes!Q$10,IF(OR(Processes!#REF!="Put here justification for overriding",Processes!#REF!=""),"Put justification for overriding!",Processes!Q$12)) | C18: =IF('Internal Systems'!Q$12="",'Internal Systems'!Q$10,IF(OR('Internal Systems'!#REF!="Put here justification for overriding",'Internal Systems'!#REF!=""),"Put justification for overriding!",'Internal Systems'!Q$12)) | D18: =IF(External!Q$13="",External!Q$11,IF(OR(External!#REF!="Put here justification for overriding",External!#REF!=""),"Put justification for overriding!",External!Q$13))
A19: =IF('Internal People & Staff'!R$13="",'Internal People & Staff'!R$11,IF(OR('Internal People & Staff'!#REF!="Put here justification for overriding",'Internal People & Staff'!#REF!=""),"Put justification for overriding!",'Internal People & Staff'!R$13)) | B19: =IF(Processes!R$12="",Processes!R$10,IF(OR(Processes!#REF!="Put here justification for overriding",Processes!#REF!=""),"Put justification for overriding!",Processes!R$12)) | C19: =IF('Internal Systems'!R$12="",'Internal Systems'!R$10,IF(OR('Internal Systems'!#REF!="Put here justification for overriding",'Internal Systems'!#REF!=""),"Put justification for overriding!",'Internal Systems'!R$12)) | D19: =IF(External!R$13="",External!R$11,IF(OR(External!#REF!="Put here justification for overriding",External!#REF!=""),"Put justification for overriding!",External!R$13))
A20: =IF('Internal People & Staff'!S$13="",'Internal People & Staff'!S$11,IF(OR('Internal People & Staff'!#REF!="Put here justification for overriding",'Internal People & Staff'!#REF!=""),"Put justification for overriding!",'Internal People & Staff'!S$13)) | B20: =IF(Processes!S$12="",Processes!S$10,IF(OR(Processes!#REF!="Put here justification for overriding",Processes!#REF!=""),"Put justification for overriding!",Processes!S$12)) | C20: =IF('Internal Systems'!S$12="",'Internal Systems'!S$10,IF(OR('Internal Systems'!#REF!="Put here justification for overriding",'Internal Systems'!#REF!=""),"Put justification for overriding!",'Internal Systems'!S$12)) | D20: =IF(External!S$13="",External!S$11,IF(OR(External!#REF!="Put here justification for overriding",External!#REF!=""),"Put justification for overriding!",External!S$13))
A21: =IF('Internal People & Staff'!T$13="",'Internal People & Staff'!T$11,IF(OR('Internal People & Staff'!#REF!="Put here justification for overriding",'Internal People & Staff'!#REF!=""),"Put justification for overriding!",'Internal People & Staff'!T$13)) | B21: =IF(Processes!T$12="",Processes!T$10,IF(OR(Processes!#REF!="Put here justification for overriding",Processes!#REF!=""),"Put justification for overriding!",Processes!T$12)) | C21: =IF('Internal Systems'!T$12="",'Internal Systems'!T$10,IF(OR('Internal Systems'!#REF!="Put here justification for overriding",'Internal Systems'!#REF!=""),"Put justification for overriding!",'Internal Systems'!T$12)) | D21: =IF(External!T$13="",External!T$11,IF(OR(External!#REF!="Put here justification for overriding",External!#REF!=""),"Put justification for overriding!",External!T$13))
A22: =IF('Internal People & Staff'!U$13="",'Internal People & Staff'!U$11,IF(OR('Internal People & Staff'!#REF!="Put here justification for overriding",'Internal People & Staff'!#REF!=""),"Put justification for overriding!",'Internal People & Staff'!U$13)) | B22: =IF(Processes!U$12="",Processes!U$10,IF(OR(Processes!#REF!="Put here justification for overriding",Processes!#REF!=""),"Put justification for overriding!",Processes!U$12)) | C22: =IF('Internal Systems'!U$12="",'Internal Systems'!U$10,IF(OR('Internal Systems'!#REF!="Put here justification for overriding",'Internal Systems'!#REF!=""),"Put justification for overriding!",'Internal Systems'!U$12)) | D22: =IF(External!U$13="",External!U$11,IF(OR(External!#REF!="Put here justification for overriding",External!#REF!=""),"Put justification for overriding!",External!U$13))
A23: =IF('Internal People & Staff'!V$13="",'Internal People & Staff'!V$11,IF(OR('Internal People & Staff'!#REF!="Put here justification for overriding",'Internal People & Staff'!#REF!=""),"Put justification for overriding!",'Internal People & Staff'!V$13)) | B23: =IF(Processes!V$12="",Processes!V$10,IF(OR(Processes!#REF!="Put here justification for overriding",Processes!#REF!=""),"Put justification for overriding!",Processes!V$12)) | C23: =IF('Internal Systems'!V$12="",'Internal Systems'!V$10,IF(OR('Internal Systems'!#REF!="Put here justification for overriding",'Internal Systems'!#REF!=""),"Put justification for overriding!",'Internal Systems'!V$12)) | D23: =IF(External!V$13="",External!V$11,IF(OR(External!#REF!="Put here justification for overriding",External!#REF!=""),"Put justification for overriding!",External!V$13))
A24: =IF('Internal People & Staff'!W$13="",'Internal People & Staff'!W$11,IF(OR('Internal People & Staff'!#REF!="Put here justification for overriding",'Internal People & Staff'!#REF!=""),"Put justification for overriding!",'Internal People & Staff'!W$13)) | B24: =IF(Processes!W$12="",Processes!W$10,IF(OR(Processes!#REF!="Put here justification for overriding",Processes!#REF!=""),"Put justification for overriding!",Processes!W$12)) | C24: =IF('Internal Systems'!W$12="",'Internal Systems'!W$10,IF(OR('Internal Systems'!#REF!="Put here justification for overriding",'Internal Systems'!#REF!=""),"Put justification for overriding!",'Internal Systems'!W$12)) | D24: =IF(External!W$13="",External!W$11,IF(OR(External!#REF!="Put here justification for overriding",External!#REF!=""),"Put justification for overriding!",External!W$13))
A25: =IF('Internal People & Staff'!X$13="",'Internal People & Staff'!X$11,IF(OR('Internal People & Staff'!#REF!="Put here justification for overriding",'Internal People & Staff'!#REF!=""),"Put justification for overriding!",'Internal People & Staff'!X$13)) | B25: =IF(Processes!X$12="",Processes!X$10,IF(OR(Processes!#REF!="Put here justification for overriding",Processes!#REF!=""),"Put justification for overriding!",Processes!X$12)) | C25: =IF('Internal Systems'!X$12="",'Internal Systems'!X$10,IF(OR('Internal Systems'!#REF!="Put here justification for overriding",'Internal Systems'!#REF!=""),"Put justification for overriding!",'Internal Systems'!X$12)) | D25: =IF(External!X$13="",External!X$11,IF(OR(External!#REF!="Put here justification for overriding",External!#REF!=""),"Put justification for overriding!",External!X$13))
A26: =IF('Internal People & Staff'!Y$13="",'Internal People & Staff'!Y$11,IF(OR('Internal People & Staff'!#REF!="Put here justification for overriding",'Internal People & Staff'!#REF!=""),"Put justification for overriding!",'Internal People & Staff'!Y$13)) | B26: =IF(Processes!Y$12="",Processes!Y$10,IF(OR(Processes!#REF!="Put here justification for overriding",Processes!#REF!=""),"Put justification for overriding!",Processes!Y$12)) | C26: =IF('Internal Systems'!Y$12="",'Internal Systems'!Y$10,IF(OR('Internal Systems'!#REF!="Put here justification for overriding",'Internal Systems'!#REF!=""),"Put justification for overriding!",'Internal Systems'!Y$12)) | D26: =IF(External!Y$13="",External!Y$11,IF(OR(External!#REF!="Put here justification for overriding",External!#REF!=""),"Put justification for overriding!",External!Y$13))
A27: =IF('Internal People & Staff'!Z$13="",'Internal People & Staff'!Z$11,IF(OR('Internal People & Staff'!#REF!="Put here justification for overriding",'Internal People & Staff'!#REF!=""),"Put justification for overriding!",'Internal People & Staff'!Z$13)) | B27: =IF(Processes!Z$12="",Processes!Z$10,IF(OR(Processes!#REF!="Put here justification for overriding",Processes!#REF!=""),"Put justification for overriding!",Processes!Z$12)) | C27: =IF('Internal Systems'!Z$12="",'Internal Systems'!Z$10,IF(OR('Internal Systems'!#REF!="Put here justification for overriding",'Internal Systems'!#REF!=""),"Put justification for overriding!",'Internal Systems'!Z$12)) | D27: =IF(External!Z$13="",External!Z$11,IF(OR(External!#REF!="Put here justification for overriding",External!#REF!=""),"Put justification for overriding!",External!Z$13))
A28: =IF('Internal People & Staff'!AA$13="",'Internal People & Staff'!AA$11,IF(OR('Internal People & Staff'!#REF!="Put here justification for overriding",'Internal People & Staff'!#REF!=""),"Put justification for overriding!",'Internal People & Staff'!AA$13)) | B28: =IF(Processes!AA$12="",Processes!AA$10,IF(OR(Processes!#REF!="Put here justification for overriding",Processes!#REF!=""),"Put justification for overriding!",Processes!AA$12)) | C28: =IF('Internal Systems'!AA$12="",'Internal Systems'!AA$10,IF(OR('Internal Systems'!#REF!="Put here justification for overriding",'Internal Systems'!#REF!=""),"Put justification for overriding!",'Internal Systems'!AA$12)) | D28: =IF(External!AA$13="",External!AA$11,IF(OR(External!#REF!="Put here justification for overriding",External!#REF!=""),"Put justification for overriding!",External!AA$13))
A29: =IF('Internal People & Staff'!AB$13="",'Internal People & Staff'!AB$11,IF(OR('Internal People & Staff'!#REF!="Put here justification for overriding",'Internal People & Staff'!#REF!=""),"Put justification for overriding!",'Internal People & Staff'!AB$13)) | B29: =IF(Processes!AB$12="",Processes!AB$10,IF(OR(Processes!#REF!="Put here justification for overriding",Processes!#REF!=""),"Put justification for overriding!",Processes!AB$12)) | C29: =IF('Internal Systems'!AB$12="",'Internal Systems'!AB$10,IF(OR('Internal Systems'!#REF!="Put here justification for overriding",'Internal Systems'!#REF!=""),"Put justification for overriding!",'Internal Systems'!AB$12)) | D29: =IF(External!AB$13="",External!AB$11,IF(OR(External!#REF!="Put here justification for overriding",External!#REF!=""),"Put justification for overriding!",External!AB$13))
A30: =IF('Internal People & Staff'!AC$13="",'Internal People & Staff'!AC$11,IF(OR('Internal People & Staff'!#REF!="Put here justification for overriding",'Internal People & Staff'!#REF!=""),"Put justification for overriding!",'Internal People & Staff'!AC$13)) | B30: =IF(Processes!AC$12="",Processes!AC$10,IF(OR(Processes!#REF!="Put here justification for overriding",Processes!#REF!=""),"Put justification for overriding!",Processes!AC$12)) | C30: =IF('Internal Systems'!AC$12="",'Internal Systems'!AC$10,IF(OR('Internal Systems'!#REF!="Put here justification for overriding",'Internal Systems'!#REF!=""),"Put justification for overriding!",'Internal Systems'!AC$12)) | D30: =IF(External!AC$13="",External!AC$11,IF(OR(External!#REF!="Put here justification for overriding",External!#REF!=""),"Put justification for overriding!",External!AC$13))
A31: =IF('Internal People & Staff'!AD$13="",'Internal People & Staff'!AD$11,IF(OR('Internal People & Staff'!#REF!="Put here justification for overriding",'Internal People & Staff'!#REF!=""),"Put justification for overriding!",'Internal People & Staff'!AD$13)) | B31: =IF(Processes!AD$12="",Processes!AD$10,IF(OR(Processes!#REF!="Put here justification for overriding",Processes!#REF!=""),"Put justification for overriding!",Processes!AD$12)) | C31: =IF('Internal Systems'!AD$12="",'Internal Systems'!AD$10,IF(OR('Internal Systems'!#REF!="Put here justification for overriding",'Internal Systems'!#REF!=""),"Put justification for overriding!",'Internal Systems'!AD$12)) | D31: =IF(External!AD$13="",External!AD$11,IF(OR(External!#REF!="Put here justification for overriding",External!#REF!=""),"Put justification for overriding!",External!AD$13))
A32: =IF('Internal People & Staff'!AE$13="",'Internal People & Staff'!AE$11,IF(OR('Internal People & Staff'!#REF!="Put here justification for overriding",'Internal People & Staff'!#REF!=""),"Put justification for overriding!",'Internal People & Staff'!AE$13)) | B32: =IF(Processes!AE$12="",Processes!AE$10,IF(OR(Processes!#REF!="Put here justification for overriding",Processes!#REF!=""),"Put justification for overriding!",Processes!AE$12)) | C32: =IF('Internal Systems'!AE$12="",'Internal Systems'!AE$10,IF(OR('Internal Systems'!#REF!="Put here justification for overriding",'Internal Systems'!#REF!=""),"Put justification for overriding!",'Internal Systems'!AE$12)) | D32: =IF(External!AE$13="",External!AE$11,IF(OR(External!#REF!="Put here justification for overriding",External!#REF!=""),"Put justification for overriding!",External!AE$13))
A33: =IF('Internal People & Staff'!AF$13="",'Internal People & Staff'!AF$11,IF(OR('Internal People & Staff'!#REF!="Put here justification for overriding",'Internal People & Staff'!#REF!=""),"Put justification for overriding!",'Internal People & Staff'!AF$13)) | B33: =IF(Processes!AF$12="",Processes!AF$10,IF(OR(Processes!#REF!="Put here justification for overriding",Processes!#REF!=""),"Put justification for overriding!",Processes!AF$12)) | C33: =IF('Internal Systems'!AF$12="",'Internal Systems'!AF$10,IF(OR('Internal Systems'!#REF!="Put here justification for overriding",'Internal Systems'!#REF!=""),"Put justification for overriding!",'Internal Systems'!AF$12)) | D33: =IF(External!AF$13="",External!AF$11,IF(OR(External!#REF!="Put here justification for overriding",External!#REF!=""),"Put justification for overriding!",External!AF$13))
A34: =IF('Internal People & Staff'!AG$13="",'Internal People & Staff'!AG$11,IF(OR('Internal People & Staff'!#REF!="Put here justification for overriding",'Internal People & Staff'!#REF!=""),"Put justification for overriding!",'Internal People & Staff'!AG$13)) | B34: =IF(Processes!AG$12="",Processes!AG$10,IF(OR(Processes!#REF!="Put here justification for overriding",Processes!#REF!=""),"Put justification for overriding!",Processes!AG$12)) | C34: =IF('Internal Systems'!AG$12="",'Internal Systems'!AG$10,IF(OR('Internal Systems'!#REF!="Put here justification for overriding",'Internal Systems'!#REF!=""),"Put justification for overriding!",'Internal Systems'!AG$12)) | D34: =IF(External!AG$13="",External!AG$11,IF(OR(External!#REF!="Put here justification for overriding",External!#REF!=""),"Put justification for overriding!",External!AG$13))
A35: =IF('Internal People & Staff'!AH$13="",'Internal People & Staff'!AH$11,IF(OR('Internal People & Staff'!#REF!="Put here justification for overriding",'Internal People & Staff'!#REF!=""),"Put justification for overriding!",'Internal People & Staff'!AH$13)) | B35: =IF(Processes!AH$12="",Processes!AH$10,IF(OR(Processes!#REF!="Put here justification for overriding",Processes!#REF!=""),"Put justification for overriding!",Processes!AH$12)) | C35: =IF('Internal Systems'!AH$12="",'Internal Systems'!AH$10,IF(OR('Internal Systems'!AI$12="Put here justification for overriding",'Internal Systems'!AI$12=""),"Put justification for overriding!",'Internal Systems'!AH$12)) | D35: =IF(External!AH$13="",External!AH$11,IF(OR(External!#REF!="Put here justification for overriding",External!#REF!=""),"Put justification for overriding!",External!AH$13))

Sheet Processes
A1: Risk Assessment for Risk Category Processes
B3: Audit No. | C3: ='Audit conclusion'!$D$3 -> 2025-045 Cyber and Information Security | D3: Explanation and Guidance | E3: ='Internal People & Staff'!E3 -> AU-109-02-Cyber & IS Strategy and Design | F3: ='Internal People & Staff'!F3 -> AU-109-08-ICT Incident Management | G3: ='Internal People & Staff'!G3 -> AU-109-09-Cyber & IS Prevention | H3: ='Internal People & Staff'!H3 -> AU-109-10-Cyber & IS Detection | I3: ='Internal People & Staff'!I3 -> AU-109-11-Cyber & IS Control functions (2LoD) | J3: ='Internal People & Staff'!J3 -> AU-109-12-Threat Intelligence | K3: ='Internal People & Staff'!K3 -> AU-121-04-CSDR Cyber & IS | L3: ='Internal People & Staff'!L3 -> 0 | ... AH3: ='Internal People & Staff'!AH3 -> 0
A4: Criteria for inherent risk | E4: Score | F4: Score | G4: Score | H4: Score | I4: Score | J4: Score | K4: Score | L4: Score | M4: Score | N4: Score | O4: Score | P4: Score | Q4: Score | R4: Score | S4: Score | T4: Score | U4: Score | V4: Score | W4: Score | X4: Score | Y4: Score | Z4: Score | AA4: Score | AB4: Score | AC4: Score | AD4: Score | AE4: Score | AF4: Score | AG4: Score | AH4: Score
A5: 1 | B5: New Process or Changes in Process | C5: High - Newly established process, significant changes in process Medium - major changes in process Low - Insignificant changes in process or products N/A is not used for this criteria | D5: Newly established processes are more exposed to low process maturity and therefore have inherently higher process risk. The states of maturity of a process (initial, repeatable, defined, managed, optimized) describe an improvement path from an ad-hoc and generally not standardized, immature process to a mature (optimized), disciplined process focused on continuous improvement. | E5: 2 | F5: 3 | G5: 2 | H5: 2 | I5: 2 | J5: 2 | K5: n/a | L5: 2
A6: 2 | B6: Process Stakeholders | C6: High - Process interacting with areas outside DBG (external stakeholders/clients/regulators) Medium - Internally conducted process is under management attention (report to committee or board) Low - Internally conducted process with limited visibility (process operator and line management) N/A is not used for this criteria | D6: Processes interacting with areas outside DBG (e.g. client interaction, regulator, public) have a higher visibility than processes which are conducted internally. A failure in highly visible processes might have a higher contribution to the exposure of reputational risk. | E6: 2 | F6: 3 | G6: 3 | H6: 3 | I6: 2 | J6: 1 | K6: n/a | L6: 3
A7: 3 | B7: Confidentiality Level of Process | C7: High - strictly confidential information is processed (e.g. strategy papers, unpublished trade information, portfolio information, information that enables insider trading) Medium - Confidential information (e.g. company internal information) is processed, but no strictly confidential information Low - Internal and lower classified information is processed N/A is not used for this criteria | D7: Inadequate handling of confidential may result in unauthorized knowledge and use of confidential information. A process reaches the next highest confidentiality level as soon as any kind of information classified with the confidentiality level is processed. Public: Information intended & authorized for general use inside & outside DBG Internal: Information, which is intended to use only within projects & organizational contexts Confidential: Sensitive information intended for the use by a restricted group of people Strictly Confidential: The most sensitive information intended for the use within a very limited group of people on management level. Typically protected by regulation, law. | E7: 3 | F7: 2 | G7: 3 | H7: 3 | I7: 2 | J7: 2 | K7: n/a | L7: 3
A8: 4 | B8: Process Criticality | C8: High - Mission critical: highest criticality with maximum quantitative and/or qualitative impact Medium: Essential - impact could be important but not maximum Low - Necessary: Not impacting business until unavailability of 1 week not exceeded / Desirable: Not impacting throughout unavailability of 1 week N/A is not used for this criteria | D8: High process criticality indicates that a process is of outstanding importance for the viability of DBG's business. In accordance to the criticality, unavailability of these processes might have a higher contribution to the quantitative or qualitative impact. The criteria attributes correspond to the criticality assessment criteria attributes for business activities of the BIA guideline. Qualitative impact types include: • Operational impact • Customer claims, penalties or compensations • Loss of customers or revenues • External interdependency and market stability • Reputational damage • Regulatory compliance Quantitative impact mainly focuses on the potential financial impact. | E8: 2 | F8: 3 | G8: 3 | H8: 3 | I8: 2 | J8: 2 | K8: n/a | L8: 2
C9: Average | E9: =IFERROR(IF(COUNTBLANK(E4:E8)>0,"",SUM(E4:E8)/COUNTIF(E4:E8,">=0")),"") -> 2.25 | F9: =IFERROR(IF(COUNTBLANK(F5:F8)>0,"",(SUM(F5:F8)/COUNTIF(F5:F8,">=0"))),"") -> 2.75 | G9: =IFERROR(IF(COUNTBLANK(G5:G8)>0,"",(SUM(G5:G8)/COUNTIF(G5:G8,">=0"))),"") -> 2.75 | H9: =IFERROR(IF(COUNTBLANK(H5:H8)>0,"",(SUM(H5:H8)/COUNTIF(H5:H8,">=0"))),"") -> 2.75 | I9: =IFERROR(IF(COUNTBLANK(I5:I8)>0,"",(SUM(I5:I8)/COUNTIF(I5:I8,">=0"))),"") -> 2 | J9: =IFERROR(IF(COUNTBLANK(J5:J8)>0,"",(SUM(J5:J8)/COUNTIF(J5:J8,">=0"))),"") -> 1.75 | K9: =IFERROR(IF(COUNTBLANK(K5:K8)>0,"",(SUM(K5:K8)/COUNTIF(K5:K8,">=0"))),"") | L9: =IFERROR(IF(COUNTBLANK(L4:L8)>0,"",SUM(L4:L8)/COUNTIF(L4:L8,">=0")),"") -> 2.5 | M9: =IFERROR(IF(COUNTBLANK(M5:M8)>0,"",(SUM(M5:M8)/COUNTIF(M5:M8,">=0"))),"") | N9: =IFERROR(IF(COUNTBLANK(N5:N8)>0,"",(SUM(N5:N8)/COUNTIF(N5:N8,">=0"))),"") | O9: =IFERROR(IF(COUNTBLANK(O5:O8)>0,"",(SUM(O5:O8)/COUNTIF(O5:O8,">=0"))),"") | P9: =IFERROR(IF(COUNTBLANK(P5:P8)>0,"",(SUM(P5:P8)/COUNTIF(P5:P8,">=0"))),"") | Q9: =IFERROR(IF(COUNTBLANK(Q5:Q8)>0,"",(SUM(Q5:Q8)/COUNTIF(Q5:Q8,">=0"))),"") | R9: =IFERROR(IF(COUNTBLANK(R5:R8)>0,"",(SUM(R5:R8)/COUNTIF(R5:R8,">=0"))),"") | S9: =IFERROR(IF(COUNTBLANK(S5:S8)>0,"",(SUM(S5:S8)/COUNTIF(S5:S8,">=0"))),"") | T9: =IFERROR(IF(COUNTBLANK(T5:T8)>0,"",(SUM(T5:T8)/COUNTIF(T5:T8,">=0"))),"") | ... AH9: =IFERROR(IF(COUNTBLANK(AH5:AH8)>0,"",(SUM(AH5:AH8)/COUNTIF(AH5:AH8,">=0"))),"")
C10: Calculated result to be overridden if deemed not adequate | E10: =IF(E9="","",IF(E9<1.4,"Low",(IF(AND(E9>=1.4,E9<2.4),"Medium",(IF((AND(E9>=2.4)),"High")))))) -> Medium | F10: =IF(F9="","",IF(F9<1.4,"Low",(IF(AND(F9>=1.4,F9<2.4),"Medium",(IF((AND(F9>=2.4)),"High")))))) -> High | G10: =IF(G9="","",IF(G9<1.4,"Low",(IF(AND(G9>=1.4,G9<2.4),"Medium",(IF((AND(G9>=2.4)),"High")))))) -> High | H10: =IF(H9="","",IF(H9<1.4,"Low",(IF(AND(H9>=1.4,H9<2.4),"Medium",(IF((AND(H9>=2.4)),"High")))))) -> High | I10: =IF(I9="","",IF(I9<1.4,"Low",(IF(AND(I9>=1.4,I9<2.4),"Medium",(IF((AND(I9>=2.4)),"High")))))) -> Medium | J10: =IF(J9="","",IF(J9<1.4,"Low",(IF(AND(J9>=1.4,J9<2.4),"Medium",(IF((AND(J9>=2.4)),"High")))))) -> Medium | K10: =IF(K9="","",IF(K9<1.4,"Low",(IF(AND(K9>=1.4,K9<2.4),"Medium",(IF((AND(K9>=2.4)),"High")))))) | L10: =IF(L9="","",IF(L9<1.4,"Low",(IF(AND(L9>=1.4,L9<2.4),"Medium",(IF((AND(L9>=2.4)),"High")))))) -> High | ... AH10: =IF(AH9="","",IF(AH9<1.4,"Low",(IF(AND(AH9>=1.4,AH9<2.4),"Medium",(IF((AND(AH9>=2.4)),"High"))))))
C12: Override the result / justification | F12: Medium | L12: Low
D13: Provide justification in case of the override | E13: =IF(E12>0,"Add justification","") | F13: As per BCA, L2 was not assessed in Cyber IS audit and current rating is from 2025-001 IT Operations Management Audit. Standard Incident Management process is followed across DBG as observed in the 2025-001 IT Operations Management, L2 controls are the same. These have been shown as mature in the past and this year, too | G13: =IF(G12>0,"Add justification","") | H13: =IF(H12>0,"Add justification","") | J13: =IF(J12>0,"Add justification","") | L13: =IF(L12>0,"Add justification","") -> Add justification | M13: =IF(M12>0,"Add justification","") | N13: =IF(N12>0,"Add justification","") | O13: =IF(O12>0,"Add justification","") | P13: =IF(P12>0,"Add justification","") | Q13: =IF(Q12>0,"Add justification","") | R13: =IF(R12>0,"Add justification","") | S13: =IF(S12>0,"Add justification","") | ... AH13: =IF(AH12>0,"Add justification","")
C14: Result of the last risk assessment (Low, Medium, High) | E14: High | F14: Medium | G14: High | H14: High
D15: Provide justification if the risk assessment result changed compared to the previous risk assessment | E15: Regarding the Process, individual ratings add up to Medium as pointed out above are driving the rating lower than it was previously in 2024. Applying a more severe/conservative outlook to the processes’ inherent risks - from last year assessment, the newly formed DBG Guidelines were published in January and aligned to DORA requirements. Group Security Procedures were still underworks with target to align them with DORA requirments and DBG Guidelines by end of 2025 (as per annual review cycle and tracked in DORA Program). | G15: No change | H15: No change | I15: As per BCA, L2 was not assessed in current audit. No previous assessment was available. IA assessment rating is supported by open S3/S2 findings/CAP from 2024-063 Technology Governance | J15: Not assessed in previous audit as separate L2 - current assessment rated as Medium

Sheet Internal Systems
A1: Risk Assessment for Risk Category Internal Systems
B3: =Processes!B3 -> Audit No. | C3: ='Audit conclusion'!$D$3 -> 2025-045 Cyber and Information Security | D3: Explanation and Guidance | E3: ='Internal People & Staff'!E3 -> AU-109-02-Cyber & IS Strategy and Design | F3: ='Internal People & Staff'!F3 -> AU-109-08-ICT Incident Management | G3: ='Internal People & Staff'!G3 -> AU-109-09-Cyber & IS Prevention | H3: ='Internal People & Staff'!H3 -> AU-109-10-Cyber & IS Detection | I3: ='Internal People & Staff'!I3 -> AU-109-11-Cyber & IS Control functions (2LoD) | J3: ='Internal People & Staff'!J3 -> AU-109-12-Threat Intelligence | K3: ='Internal People & Staff'!K3 -> AU-121-04-CSDR Cyber & IS | L3: ='Internal People & Staff'!L3 -> 0 | ... AH3: ='Internal People & Staff'!AH3 -> 0
A4: Criteria for inherent risk | E4: Score | F4: Score | G4: Score | H4: Score | I4: Score | J4: Score | K4: Score | L4: Score | M4: Score | N4: Score | O4: Score | P4: Score | Q4: Score | R4: Score | S4: Score | T4: Score | U4: Score | V4: Score | W4: Score | X4: Score | Y4: Score | Z4: Score | AA4: Score | AB4: Score | AC4: Score | AD4: Score | AE4: Score | AF4: Score | AG4: Score | AH4: Score | AI4: Rationale
A5: 1 | B5: New IT Systems/Application or Changes in IT Systems/Tools | C5: High - New IT System/Application implemented or significant changes in IT System/Application which have a huge impact on performance of the process Medium - New IT System/Application implemented or major changes in IT System/Application which have an impact on the performance of one sub-process Low - New IT System/Application implemented or changes in IT System/Application which have no or only minor impact on performance of the process | D5: Changes in IT System/Tools or introduction of new IT System/Tool should be anticipated and incorporated in the audit planning to ensure that system changes have been implemented properly and support the process performance as intended. | E5: 1 | F5: 2 | G5: 2 | H5: 2 | I5: 1 | J5: 2 | K5: n/a
A6: 2 | B6: Internally developed vs. Standard Tools | C6: High - Significant reliance on internally developed tools which have a huge impact on process performance Medium - Major reliance on customized standard tools with in-built controls which have a large impact on process performance Low - Only standard tools in use N/A is not used for this criteria | D6: In general, internal tools contain a higher risk of lower system stability or introduced vulnerabilities, compared to established standardized externally developed tools, where the source code is not available, can not change without vendor update and is proven for larger global audience | E6: 1 | F6: 2 | G6: 2 | H6: 2 | I6: 1 | J6: 2 | K6: n/a
A7: 3 | B7: Individual Data Processing (IDP)/End-User Computing | C7: High - Significant reliance on IDP (including Excel- or Access based tools) which have a huge impact on process performance Medium - Major reliance on IDP which have a large impact on process performance Low - Minor reliance on IDP or only low impact on process performance None - "N/A" | D7: In general, individual data processing/end-user computing contain a higher error susceptibility (e.g. because of required interfaces and workarounds), lower system stability and insufficient access control. Definitions and details are mentioned in the DBG Individual Data Processing Policy | E7: n/a | F7: n/a | G7: n/a | H7: n/a | I7: n/a | J7: n/a | K7: n/a
A8: 4 | B8: Dependency on Systems/Tools | C8: High - Process is highly dependent on systems/tools, process cannot be performed without system availability Medium - Major parts of the process are dependent on systems/tools, in absence of systems process can only be executed with delays or under difficult conditions Low - Minor dependency on systems/tools or process can be executed through existing alternative systems/manual workarounds N/A is not used for this criteria | D8: If the process is highly dependent on specific systems/tools, unavailability or changes of the systems/tools will affect the process execution. The degree of automation should also be considered within the assessment. Automated processes are highly dependent on the availability of tools/systems. Systems/tools in this context do not include applications and data that are available on every computer (e.g. Word, Excel etc.). | E8: 2 | F8: 2 | G8: 3 | H8: 3 | I8: 1 | J8: 2 | K8: n/a
C9: Average | E9: =IFERROR(IF(COUNTBLANK(E5:E8)>0,"",SUM(E5:E8)/COUNTIF(E5:E8,">=0")),"") -> 1.3333333 | F9: =IFERROR(IF(COUNTBLANK(F5:F8)>0,"",SUM(F5:F8)/COUNTIF(F5:F8,">=0")),"") -> 2 | G9: =IFERROR(IF(COUNTBLANK(G5:G8)>0,"",SUM(G5:G8)/COUNTIF(G5:G8,">=0")),"") -> 2.3333333 | H9: =IFERROR(IF(COUNTBLANK(H5:H8)>0,"",SUM(H5:H8)/COUNTIF(H5:H8,">=0")),"") -> 2.3333333 | I9: =IFERROR(IF(COUNTBLANK(I5:I8)>0,"",SUM(I5:I8)/COUNTIF(I5:I8,">=0")),"") -> 1 | J9: =IFERROR(IF(COUNTBLANK(J5:J8)>0,"",SUM(J5:J8)/COUNTIF(J5:J8,">=0")),"") -> 2 | K9: =IFERROR(IF(COUNTBLANK(K5:K8)>0,"",SUM(K5:K8)/COUNTIF(K5:K8,">=0")),"") | L9: =IFERROR(IF(COUNTBLANK(L5:L8)>0,"",SUM(L5:L8)/COUNTIF(L5:L8,">=0")),"") | ... AH9: =IFERROR(IF(COUNTBLANK(AH5:AH8)>0,"",SUM(AH5:AH8)/COUNTIF(AH5:AH8,">=0")),"")
C10: Calculated result to be overridden if deemed not adequate | E10: =IF(E9="","",IF(E9<1.4,"Low",(IF(AND(E9>=1.4,E9<2.4),"Medium",(IF((AND(E9>=2.4)),"High")))))) -> Low | F10: =IF(F9="","",IF(F9<1.4,"Low",(IF(AND(F9>=1.4,F9<2.4),"Medium",(IF((AND(F9>=2.4)),"High")))))) -> Medium | G10: =IF(G9="","",IF(G9<1.4,"Low",(IF(AND(G9>=1.4,G9<2.4),"Medium",(IF((AND(G9>=2.4)),"High")))))) -> Medium | H10: =IF(H9="","",IF(H9<1.4,"Low",(IF(AND(H9>=1.4,H9<2.4),"Medium",(IF((AND(H9>=2.4)),"High")))))) -> Medium | I10: =IF(I9="","",IF(I9<1.4,"Low",(IF(AND(I9>=1.4,I9<2.4),"Medium",(IF((AND(I9>=2.4)),"High")))))) -> Low | J10: =IF(J9="","",IF(J9<1.4,"Low",(IF(AND(J9>=1.4,J9<2.4),"Medium",(IF((AND(J9>=2.4)),"High")))))) -> Medium | K10: =IF(K9="","",IF(K9<1.4,"Low",(IF(AND(K9>=1.4,K9<2.4),"Medium",(IF((AND(K9>=2.4)),"High")))))) | L10: =IF(L9="","",IF(L9<1.4,"Low",(IF(AND(L9>=1.4,L9<2.4),"Medium",(IF((AND(L9>=2.4)),"High")))))) | ... AH10: =IF(AH9="","",IF(AH9<1.4,"Low",(IF(AND(AH9>=1.4,AH9<2.4),"Medium",(IF((AND(AH9>=2.4)),"High"))))))
C12: Override the result / justification | AI12: =IF(AH12="","","Put here justification for overriding")
D13: Provide justification in case of the override | E13: =IF(E12>0,"Add justification","") | F13: =IF(F12>0,"Add justification","") | G13: =IF(G12>0,"Add justification","") | H13: =IF(H12>0,"Add justification","") | I13: =IF(I12>0,"Add justification","") | J13: =IF(J12>0,"Add justification","") | L13: =IF(L12>0,"Add justification","") | M13: =IF(M12>0,"Add justification","") | N13: =IF(N12>0,"Add justification","") | O13: =IF(O12>0,"Add justification","") | P13: =IF(P12>0,"Add justification","") | Q13: =IF(Q12>0,"Add justification","") | R13: =IF(R12>0,"Add justification","") | S13: =IF(S12>0,"Add justification","") | ... AH13: =IF(AH12>0,"Add justification","")
C14: Result of the last risk assessment (Low, Medium, High) | E14: Low | F14: Medium | G14: Medium | H14: Medium
D15: Provide justification if the risk assessment result changed compared to the previous risk assessment | E15: No change | F15: As per BCA, L2 was not assessed in Cyber IS audit and current rating is from 2025-001 IT Operations Management Audit. Standard Incident Management process is followed across DBG as observed in the 2025-001 IT Operations Management, L2 controls are the same. These have been shown as mature in the past and this year, too | G15: No change | H15: No change | I15: As per BCA, L2 was not assessed in current audit. No previous assessment was available. IA assessment rating is supported by open S3/S2 findings/CAP from 2024-063 Technology Governance | J15: Not assessed in previous audit as separate L2 - current assessment rated as Medium

Sheet External
A1: Risk Assessment for Risk Category External
B3: =Processes!B3 -> Audit No. | C3: ='Audit conclusion'!$D$3 -> 2025-045 Cyber and Information Security | D3: Explanation and Guidance | E3: ='Internal People & Staff'!E3 -> AU-109-02-Cyber & IS Strategy and Design | F3: ='Internal People & Staff'!F3 -> AU-109-08-ICT Incident Management | G3: ='Internal People & Staff'!G3 -> AU-109-09-Cyber & IS Prevention | H3: ='Internal People & Staff'!H3 -> AU-109-10-Cyber & IS Detection | I3: ='Internal People & Staff'!I3 -> AU-109-11-Cyber & IS Control functions (2LoD) | J3: ='Internal People & Staff'!J3 -> AU-109-12-Threat Intelligence | K3: ='Internal People & Staff'!K3 -> AU-121-04-CSDR Cyber & IS | L3: ='Internal People & Staff'!L3 -> 0 | ... AH3: ='Internal People & Staff'!AH3 -> 0
A4: Criteria for inherent risk | E4: Score | F4: Score | G4: Score | H4: Score | I4: Score | J4: Score | K4: Score | L4: Score | M4: Score | N4: Score | O4: Score | P4: Score | Q4: Score | R4: Score | S4: Score | T4: Score | U4: Score | V4: Score | W4: Score | X4: Score | Y4: Score | Z4: Score | AA4: Score | AB4: Score | AC4: Score | AD4: Score | AE4: Score | AF4: Score | AG4: Score | AH4: Score
A5: 1 | B5: External Fraud Incentives | C5: High - Process highly exposed to external fraud due to possibility for severe illicit enrichment (e.g. cyber attacks, money laundering, fraudulent transaction instructions, theft of transaction data of market participants, external market manipulation) driven by handling of sensitive data and financial transactions Medium - Process is exposed to external fraud due to possible illicit enrichment limited to the volume of internal transactions/inventory (e.g. creditor invoices, theft) Low - Negligible exposure due to moderate or no possible illicit enrichment N/A is not used for this criteria | D5: Depending on the data processed fraud activity could lead to increased financial or non-financial (reputational impact, impact on customers, regulatory actions) damage. Typically correlates with internal fraud exposure, but goes beyond (e.g. external market manipulation, external transaction manipulation). | E5: 1 | F5: 1 | G5: 3 | H5: 3 | I5: 1 | J5: 1 | K5: n/a
A6: 2 | B6: Exposure to Regulator's Scrutiny | C6: High - Significantly and regularly exposed to external reviews based on applicable multiple laws, regulations/jurisdictions Medium - Exposed to occasional external review based on applicable law or regulation Low - No exposure to external review N/A is not used for this criteria | D6: Regulatory risk increases with the number of regulations (and IT regulations, e.g. KRITIS) to be complied with. Regulatory changes should be anticipated. It should be ensured that compliance with changing regulations is ensured, before the respective regulation becomes enforceable. | E6: 2 | F6: 3 | G6: 3 | H6: 3 | I6: 2 | J6: 2 | K6: n/a
A7: 3 | B7: External supplier utilization (including intra-group outsourcing) | C7: High - Significant parts of the process are executed by external suppliers Medium - Major parts of the process are executed by external suppliers Low - Only minor parts of the process are executed by external suppliers/ No part of the process is executed by external suppliers N/A is not used for this criteria | D7: The degree of outsourcing of substantial processes indicates the dependency from external suppliers. | E7: 2 | F7: 3 | G7: 3 | H7: 3 | I7: 1 | J7: 2 | K7: n/a
A8: 4 | B8: Data Protection according to GDPR | C8: High - Processing and/or controlling of personal data is performed on behalf of external (non-DBAG) entities and/orDBAG entities outside of the EU. Medium – Processes personal data for its own purpose or for the purpose of other entities within the Group Low - Controls personal data for its own purposes N/A is not applicable here | D8: If personal information is processed, GDPR requirements apply, according to internal guidelines (Data Protection Impact Assessment). Processing and/or controlling of personal data on behalf of entities outside of the EU result in a high exposure of external regulation relating to GDPR compared to local requirements (outside of EU). | E8: 2 | F8: 1 | G8: 3 | H8: 3 | I8: 1 | J8: 2 | K8: n/a
A9: 5 | B9: Dependency on local company infrastructure/flexibility of workplace and staff availability | C9: High - Performance of work would not be possible from another site or alternative group of staff only after significant efforts to set up / recover alternative structures (weeks, if not months) Medium - Performing the respective areas work at another site or alternative group of staff is only possible after implementation of an alternative solution (e.g. according to the business continuity plan) (several days) Low - The respective areas work could easily be performed at another site or with an alternative group of staff (within one day) | D9: The lower the degree of dependency on local infrastructure, like personal computers and data only available or accessible at the company site or specific group of staff, the lower the risk proneness to external events. | E9: 1 | F9: 1 | G9: 2 | H9: 2 | I9: 1 | J9: 2 | K9: n/a
C10: Average | E10: =IFERROR(IF(COUNTBLANK(E5:E9)>0,"",SUM(E5:E9)/COUNTIF(E5:E9,">=0")),"") -> 1.6 | F10: =IFERROR(IF(COUNTBLANK(F5:F9)>0,"",SUM(F5:F9)/COUNTIF(F5:F9,">=0")),"") -> 1.8 | G10: =IFERROR(IF(COUNTBLANK(G5:G9)>0,"",SUM(G5:G9)/COUNTIF(G5:G9,">=0")),"") -> 2.8 | H10: =IFERROR(IF(COUNTBLANK(H5:H9)>0,"",SUM(H5:H9)/COUNTIF(H5:H9,">=0")),"") -> 2.8 | I10: =IFERROR(IF(COUNTBLANK(I5:I9)>0,"",SUM(I5:I9)/COUNTIF(I5:I9,">=0")),"") -> 1.2 | J10: =IFERROR(IF(COUNTBLANK(J5:J9)>0,"",SUM(J5:J9)/COUNTIF(J5:J9,">=0")),"") -> 1.8 | K10: =IFERROR(IF(COUNTBLANK(K5:K9)>0,"",SUM(K5:K9)/COUNTIF(K5:K9,">=0")),"") | L10: =IFERROR(IF(COUNTBLANK(L5:L9)>0,"",SUM(L5:L9)/COUNTIF(L5:L9,">=0")),"") | ... AH10: =IFERROR(IF(COUNTBLANK(AH5:AH9)>0,"",SUM(AH5:AH9)/COUNTIF(AH5:AH9,">=0")),"")
C11: Calculated result to be overridden if deemed not adequate | E11: =IF(E10="","",IF(E10<1.4,"Low",(IF(AND(E10>=1.4,E10<2.4),"Medium",(IF((AND(E10>=2.4)),"High")))))) -> Medium | F11: =IF(F10="","",IF(F10<1.4,"Low",(IF(AND(F10>=1.4,F10<2.4),"Medium",(IF((AND(F10>=2.4)),"High")))))) -> Medium | G11: =IF(G10="","",IF(G10<1.4,"Low",(IF(AND(G10>=1.4,G10<2.4),"Medium",(IF((AND(G10>=2.4)),"High")))))) -> High | H11: =IF(H10="","",IF(H10<1.4,"Low",(IF(AND(H10>=1.4,H10<2.4),"Medium",(IF((AND(H10>=2.4)),"High")))))) -> High | I11: =IF(I10="","",IF(I10<1.4,"Low",(IF(AND(I10>=1.4,I10<2.4),"Medium",(IF((AND(I10>=2.4)),"High")))))) -> Low | J11: =IF(J10="","",IF(J10<1.4,"Low",(IF(AND(J10>=1.4,J10<2.4),"Medium",(IF((AND(J10>=2.4)),"High")))))) -> Medium | K11: =IF(K10="","",IF(K10<1.4,"Low",(IF(AND(K10>=1.4,K10<2.4),"Medium",(IF((AND(K10>=2.4)),"High")))))) | L11: =IF(L10="","",IF(L10<1.4,"Low",(IF(AND(L10>=1.4,L10<2.4),"Medium",(IF((AND(L10>=2.4)),"High")))))) | ... AH11: =IF(AH10="","",IF(AH10<1.4,"Low",(IF(AND(AH10>=1.4,AH10<2.4),"Medium",(IF((AND(AH10>=2.4)),"High"))))))
C13: Override the result / justification
D14: Provide justification in case of the override | E14: =IF(E13>0,"Add justification","") | G14: =IF(G13>0,"Add justification","") | H14: =IF(H13>0,"Add justification","") | I14: =IF(I13>0,"Add justification","") | J14: =IF(J13>0,"Add justification","") | K14: =IF(K13>0,"Add justification","") | L14: =IF(L13>0,"Add justification","") | M14: =IF(M13>0,"Add justification","") | N14: =IF(N13>0,"Add justification","") | ... AH14: =IF(AH13>0,"Add justification","")
C15: Result of the last risk assessment (Low, Medium, High) | E15: Medium | F15: Low | G15: High | H15: High
D16: Provide justification if the risk assessment result changed compared to the previous risk assessment | E16: No change | F16: As per BCA, L2 was not assessed in Cyber IS audit and current rating is from 2025-001 IT Operations Management Audit. Standard Incident Management process is followed across DBG as observed in the 2025-001 IT Operations Management, L2 controls are the same. These have been shown as mature in the past and this year, too | G16: No change | H16: No change | I16: As per BCA, L2 was not assessed in current audit. No previous assessment was available. IA assessment rating is supported by open S3/S2 findings/CAP from 2024-063 Technology Governance | J16: Not assessed in previous audit as separate L2 - current assessment rated as Medium

Sheet IS Risk Assessment
A1: Risk Assessment for Risk Category Information Security
B3: =[1]Processes!B3 -> Audit No. | C3: ='Audit conclusion'!$D$3 -> 2025-045 Cyber and Information Security | D3: Explanation and Guidance | E3: ='Internal People & Staff'!E3 -> AU-109-02-Cyber & IS Strategy and Design | F3: Comment (Mandatory field) | G3: ='Internal People & Staff'!F3 -> AU-109-08-ICT Incident Management | H3: Comment (Mandatory field) | I3: ='Internal People & Staff'!G3 -> AU-109-09-Cyber & IS Prevention | J3: Comment (Mandatory field) | K3: ='Internal People & Staff'!H3 -> AU-109-10-Cyber & IS Detection | L3: Comment (Mandatory field) | M3: ='Internal People & Staff'!I3 -> AU-109-11-Cyber & IS Control functions (2LoD) | N3: Comment (Mandatory field) | O3: ='Internal People & Staff'!J3 -> AU-109-12-Threat Intelligence | P3: Comment (Mandatory field) | Q3: ='Internal People & Staff'!K3 -> AU-121-04-CSDR Cyber & IS | R3: Comment (Mandatory field) | S3: ='Internal People & Staff'!L3 -> 0 | T3: Comment (Mandatory field) | U3: ='Internal People & Staff'!M3 -> 0 | V3: Comment (Mandatory field) | W3: ='Internal People & Staff'!N3 -> 0 | X3: Comment (Mandatory field) | Y3: ='Internal People & Staff'!O3 -> 0 | Z3: Comment (Mandatory field) | AA3: ='Internal People & Staff'!P3 -> 0 | AB3: Comment (Mandatory field) | AC3: ='Internal People & Staff'!Q3 -> 0 | AD3: Comment (Mandatory field) | AE3: ='Internal People & Staff'!R3 -> 0 | AF3: Comment (Mandatory field) | AG3: ='Internal People & Staff'!S3 -> 0 | AH3: Comment (Mandatory field) | AI3: ='Internal People & Staff'!T3 -> 0 | AJ3: Comment (Mandatory field) | AK3: ='Internal People & Staff'!U3 -> 0 | AL3: Comment (Mandatory field) | AM3: ='Internal People & Staff'!V3 -> 0 | AN3: Comment (Mandatory field) | AO3: ='Internal People & Staff'!W3 -> 0 | AP3: Comment (Mandatory field) | AQ3: ='Internal People & Staff'!X3 -> 0 | AR3: Comment (Mandatory field) | AS3: ='Internal People & Staff'!Y3 -> 0 | AT3: Comment (Mandatory field) | AU3: ='Internal People & Staff'!Z3 -> 0 | AV3: Comment (Mandatory field) | AW3: ='Internal People & Staff'!AA3 -> 0 | AX3: Comment (Mandatory field) | AY3: ='Internal People & Staff'!AB3 -> 0 | AZ3: Comment (Mandatory field) | BA3: ='Internal People & Staff'!AC3 -> 0 | BB3: Comment (Mandatory field) | BC3: ='Internal People & Staff'!AD3 -> 0 | BD3: Comment (Mandatory field) | BE3: ='Internal People & Staff'!AE3 -> 0 | BF3: Comment (Mandatory field) | BG3: ='Internal People & Staff'!AF3 -> 0 | BH3: Comment (Mandatory field) | BI3: ='Internal People & Staff'!AG3 -> 0 | BJ3: Comment (Mandatory field) | BK3: ='Internal People & Staff'!AH3 -> 0
A4: Criteria for inherent risk | E4: Score | G4: Score | I4: Score | K4: Score | M4: Score | O4: Score | Q4: Score | S4: Score | U4: Score | W4: Score | Y4: Score | AA4: Score | AC4: Score | AE4: Score | AG4: Score | AI4: Score | AK4: Score | AM4: Score | AO4: Score | AQ4: Score | AS4: Score | AU4: Score | AW4: Score | AY4: Score | BA4: Score | BC4: Score | BE4: Score | BG4: Score | BI4: Score | BK4: Score
A5: 1 | B5: IT Application risk and business risk data (Confidentiality, Integrity, and Authenticity) | C5: High - IT Applications with the potential for S4 or S3 findings (Not an identification of existing findings, but assessment of the criticality and whether IT application has the potential of having findings) given the criticality of the application. Affected data include e.g. financial data (e.g. Tax or P&L data), Personal Identifiable Information (PII), Strictly Confidential (SC) data or do have a high GDPR relevance. The business process fully rely's on data confidentiality, integrity and authenticity. Medium – IT Applications with the potential for S2 or S1 findings, (Not an identification of existing findings, but assessment of the criticality and whether IT application has the potential of having findings) given the criticality of the application. The business process is classified as medium or has a limited reliance on data confidentiality, integrity and authenticity. A second data sources exist which could be used in case of confidentiality, integrity and authenticity breaches. Low - IT Applications with the potential for Comments, given the criticality of the application. The business process itself is low or the business process does not rely on the data but can continue without the data. N/A is not used for this criteria | D5: For the IT applications in the audit scope or newly identified applications, take into account their: - Overall: data criticality of the using business process (most important) - IA's application risk assessment (as in "Guidance Paper for IT Application Coverage and Audit Strategy"); IA golden source for applications. - Group risk assessment for data confidentiality, data integrity and data authenticity (e.g. as listed in APMS) | E5: 1 | F5: Governance aspect of IS Strategy and Design. No or just limited criticality of IT Applications used in this area. | G5: 1 | H5: As per BCA, L2 was not in focus of this audit. Ratings come from process as covered in 2025-001 IT Operations Management | I5: 2 | J5: Outdated cryptography measures, expired keys, and data breaches result in inadequate protection of sensitive data and misrepresentation of control effectiveness in risk assessments. Cryptography controls need to have strengthen governance and harmonization in the related control environment across Asset Owners, Shared IT, and Product IT teams. | K5: 2 | L5: Many aspects such as Digitalization of Application Security Document, IS Risk Management, Threat Led Penetration Testing (TLPT), SSH Key Inventory (SKI), SSH Key Management (SKM), Database Activity Monitoring (DAM), gaps around the management (collection, storage) of Security Information and Event Management (SIEM) data, Advanced Persistent Threat (APT) protection, etc. were still undergoing remediation/implementation, particularly from AMELI. | M5: 1 | N5: As per BCA, L2 was not in focus of this audit. No or just limited criticality of IT Applications used in this area. | O5: 2 | P5: IT Applications relevant to two S2 findings | Q5: N/A | T5: =IF(S5>0,"Add justification","") | V5: =IF(U5>0,"Add justification","") | X5: =IF(W5>0,"Add justification","") | Z5: =IF(Y5>0,"Add justification","") | AB5: =IF(AA5>0,"Add justification","") | AD5: =IF(AC5>0,"Add justification","") | AF5: =IF(AE5>0,"Add justification","") | AH5: =IF(AG5>0,"Add justification","") | AJ5: =IF(AI5>0,"Add justification","") | AL5: =IF(AK5>0,"Add justification","") | AN5: =IF(AM5>0,"Add justification","") | AP5: =IF(AO5>0,"Add justification","") | AR5: =IF(AQ5>0,"Add justification","") | AT5: =IF(AS5>0,"Add justification","") | AV5: =IF(AU5>0,"Add justification","") | AX5: =IF(AW5>0,"Add justification","") | AZ5: =IF(AY5>0,"Add justification","") | BB5: =IF(BA5>0,"Add justification","") | BD5: =IF(BC5>0,"Add justification","") | BF5: =IF(BE5>0,"Add justification","") | BH5: =IF(BG5>0,"Add justification","") | BJ5: =IF(BI5>0,"Add justification","")
A6: 2 | B6: IDP Data concerning Confidentiality, Integrity and Authenticity | C6: High - Affected data include e.g. financial data (e.g. Tax or P&L data), Personal Identifiable Information (PII) or Strictly Confidential (SC) data. The business process fully rely's on data confidentiality, integrity and authenticity. Medium – IDPs with the potential for S2 or S1 findings (Not an identification of existing findings, but assessment of the criticality and whether IDP has the potential of having findings). The business process is classified as medium or has a limited reliance on data confidentiality, integrity and authenticity. Second data sources exist which could be used in case of confidentiality, integrity and authenticity breaches. Low - The business process itself is low or the business process does not rely on the data but can continue without the data. N/A is not used for this criteria | D6: For the IDPs in the audit scope or newly identified IDPs, take into account: - Overall: data criticality of the using business process (most important) - The risk portfolio of IPD (how many high risk, how many medium risk, how many low risk). | E6: 1 | F6: No IDPs identified during the audit. | G6: 1 | H6: As per BCA, L2 was not in focus of this audit. Ratings come from process as covered in 2025-001 IT Operations Management | I6: 1 | J6: No IDPs identified during the audit. | K6: 1 | L6: No IDPs identified during the audit. | M6: 1 | N6: As per BCA, L2 was not in focus of this audit. | O6: 1 | P6: No IDPs identified during the audit. | Q6: N/A | T6: =IF(S6>0,"Add justification","") | V6: =IF(U6>0,"Add justification","") | X6: =IF(W6>0,"Add justification","") | Z6: =IF(Y6>0,"Add justification","") | AB6: =IF(AA6>0,"Add justification","") | AD6: =IF(AC6>0,"Add justification","") | AF6: =IF(AE6>0,"Add justification","") | AH6: =IF(AG6>0,"Add justification","") | AJ6: =IF(AI6>0,"Add justification","") | AL6: =IF(AK6>0,"Add justification","") | AN6: =IF(AM6>0,"Add justification","") | AP6: =IF(AO6>0,"Add justification","") | AR6: =IF(AQ6>0,"Add justification","") | AT6: =IF(AS6>0,"Add justification","") | AV6: =IF(AU6>0,"Add justification","") | AX6: =IF(AW6>0,"Add justification","") | AZ6: =IF(AY6>0,"Add justification","") | BB6: =IF(BA6>0,"Add justification","") | BD6: =IF(BC6>0,"Add justification","") | BF6: =IF(BE6>0,"Add justification","") | BH6: =IF(BG6>0,"Add justification","") | BJ6: =IF(BI6>0,"Add justification","")
A7: 3 | B7: Outcome of IS related insights gained during the audit, e.g. discussions with senior management | C7: High - highest criticality with maximum quantitative and/or qualitative impact to IS related processes Medium: impact could be important but not maximum Low - minimum impact to IS related processes N/A is not used for this criteria | D7: Consider IS-related information obtained during fieldwork inlcuding discussions with senior management and own IA assessment | E7: 2 | F7: DORA regulation requirment fullfillment efforts through 2025. | G7: 1 | H7: As per BCA, L2 was not in focus of this audit. Ratings come from process as covered in 2025-001 IT Operations Management | I7: 2 | J7: Outdated cryptography measures, expired keys, and data breaches result in inadequate protection of sensitive data and misrepresentation of control effectiveness in risk assessments. Cryptography controls need to have strengthen governance and harmonization in the related control environment across Asset Owners, Shared IT, and Product IT teams. | K7: 2 | L7: Significant remediation efforts are underway through the DORA and AMELI programs, addressing significant gaps within this L2 area of Cyber and IS. | M7: 1 | N7: Inadequate guidelines on ‘Partner Services’ as an asset type in DBG’s APMS. | O7: 2 | P7: Segregation of duty (SoD) control deficiency for the application. From IS risk perspective impact is medium with focus on this area. | Q7: N/A | T7: =IF(S7>0,"Add justification","") | V7: =IF(U7>0,"Add justification","") | X7: =IF(W7>0,"Add justification","") | Z7: =IF(Y7>0,"Add justification","") | AB7: =IF(AA7>0,"Add justification","") | AD7: =IF(AC7>0,"Add justification","") | AF7: =IF(AE7>0,"Add justification","") | AH7: =IF(AG7>0,"Add justification","") | AJ7: =IF(AI7>0,"Add justification","") | AL7: =IF(AK7>0,"Add justification","") | AN7: =IF(AM7>0,"Add justification","") | AP7: =IF(AO7>0,"Add justification","") | AR7: =IF(AQ7>0,"Add justification","") | AT7: =IF(AS7>0,"Add justification","") | AV7: =IF(AU7>0,"Add justification","") | AX7: =IF(AW7>0,"Add justification","") | AZ7: =IF(AY7>0,"Add justification","") | BB7: =IF(BA7>0,"Add justification","") | BD7: =IF(BC7>0,"Add justification","") | BF7: =IF(BE7>0,"Add justification","") | BH7: =IF(BG7>0,"Add justification","") | BJ7: =IF(BI7>0,"Add justification","")
C8: Average | E8: =IFERROR(IF(COUNTBLANK(E5:E7)>0,"",SUM(E5:E7)/COUNTIF(E5:E7,">=0")),"") -> 1.3333333 | G8: =IFERROR(IF(COUNTBLANK(G5:G7)>0,"",SUM(G5:G7)/COUNTIF(G5:G7,">=0")),"") -> 1 | I8: =IFERROR(IF(COUNTBLANK(I5:I7)>0,"",SUM(I5:I7)/COUNTIF(I5:I7,">=0")),"") -> 1.6666667 | K8: =IFERROR(IF(COUNTBLANK(K5:K7)>0,"",SUM(K5:K7)/COUNTIF(K5:K7,">=0")),"") -> 1.6666667 | M8: =IFERROR(IF(COUNTBLANK(M5:M7)>0,"",SUM(M5:M7)/COUNTIF(M5:M7,">=0")),"") -> 1 | O8: =IFERROR(IF(COUNTBLANK(O5:O7)>0,"",SUM(O5:O7)/COUNTIF(O5:O7,">=0")),"") -> 1.6666667 | Q8: =IFERROR(IF(COUNTBLANK(Q5:Q7)>0,"",SUM(Q5:Q7)/COUNTIF(Q5:Q7,">=0")),"") | S8: =IFERROR(IF(COUNTBLANK(S5:S7)>0,"",SUM(S5:S7)/COUNTIF(S5:S7,">=0")),"") | U8: =IFERROR(IF(COUNTBLANK(U5:U7)>0,"",SUM(U5:U7)/COUNTIF(U5:U7,">=0")),"") | W8: =IFERROR(IF(COUNTBLANK(W5:W7)>0,"",SUM(W5:W7)/COUNTIF(W5:W7,">=0")),"") | Y8: =IFERROR(IF(COUNTBLANK(Y5:Y7)>0,"",SUM(Y5:Y7)/COUNTIF(Y5:Y7,">=0")),"") | AA8: =IFERROR(IF(COUNTBLANK(AA5:AA7)>0,"",SUM(AA5:AA7)/COUNTIF(AA5:AA7,">=0")),"") | AC8: =IFERROR(IF(COUNTBLANK(AC5:AC7)>0,"",SUM(AC5:AC7)/COUNTIF(AC5:AC7,">=0")),"") | AE8: =IFERROR(IF(COUNTBLANK(AE5:AE7)>0,"",SUM(AE5:AE7)/COUNTIF(AE5:AE7,">=0")),"") | AG8: =IFERROR(IF(COUNTBLANK(AG5:AG7)>0,"",SUM(AG5:AG7)/COUNTIF(AG5:AG7,">=0")),"") | AI8: =IFERROR(IF(COUNTBLANK(AI5:AI7)>0,"",SUM(AI5:AI7)/COUNTIF(AI5:AI7,">=0")),"") | AK8: =IFERROR(IF(COUNTBLANK(AK5:AK7)>0,"",SUM(AK5:AK7)/COUNTIF(AK5:AK7,">=0")),"") | AM8: =IFERROR(IF(COUNTBLANK(AM5:AM7)>0,"",SUM(AM5:AM7)/COUNTIF(AM5:AM7,">=0")),"") | AO8: =IFERROR(IF(COUNTBLANK(AO5:AO7)>0,"",SUM(AO5:AO7)/COUNTIF(AO5:AO7,">=0")),"") | AQ8: =IFERROR(IF(COUNTBLANK(AQ5:AQ7)>0,"",SUM(AQ5:AQ7)/COUNTIF(AQ5:AQ7,">=0")),"") | AS8: =IFERROR(IF(COUNTBLANK(AS5:AS7)>0,"",SUM(AS5:AS7)/COUNTIF(AS5:AS7,">=0")),"") | AU8: =IFERROR(IF(COUNTBLANK(AU5:AU7)>0,"",SUM(AU5:AU7)/COUNTIF(AU5:AU7,">=0")),"") | AW8: =IFERROR(IF(COUNTBLANK(AW5:AW7)>0,"",SUM(AW5:AW7)/COUNTIF(AW5:AW7,">=0")),"") | AY8: =IFERROR(IF(COUNTBLANK(AY5:AY7)>0,"",SUM(AY5:AY7)/COUNTIF(AY5:AY7,">=0")),"") | BA8: =IFERROR(IF(COUNTBLANK(BA5:BA7)>0,"",SUM(BA5:BA7)/COUNTIF(BA5:BA7,">=0")),"") | BC8: =IFERROR(IF(COUNTBLANK(BC5:BC7)>0,"",SUM(BC5:BC7)/COUNTIF(BC5:BC7,">=0")),"") | BE8: =IFERROR(IF(COUNTBLANK(BE5:BE7)>0,"",SUM(BE5:BE7)/COUNTIF(BE5:BE7,">=0")),"") | BG8: =IFERROR(IF(COUNTBLANK(BG5:BG7)>0,"",SUM(BG5:BG7)/COUNTIF(BG5:BG7,">=0")),"") | BI8: =IFERROR(IF(COUNTBLANK(BI5:BI7)>0,"",SUM(BI5:BI7)/COUNTIF(BI5:BI7,">=0")),"") | BK8: =IFERROR(IF(COUNTBLANK(BK5:BK7)>0,"",SUM(BK5:BK7)/COUNTIF(BK5:BK7,">=0")),"")
C9: Calculated result to be overridden if deemed not adequate | E9: =IF(E8="","",IF(E8<1.4,"Low",(IF(AND(E8>=1.4,E8<2.4),"Medium",(IF((AND(E8>=2.4)),"High")))))) -> Low | G9: =IF(G8="","",IF(G8<1.4,"Low",(IF(AND(G8>=1.4,G8<2.4),"Medium",(IF((AND(G8>=2.4)),"High")))))) -> Low | I9: =IF(I8="","",IF(I8<1.4,"Low",(IF(AND(I8>=1.4,I8<2.4),"Medium",(IF((AND(I8>=2.4)),"High")))))) -> Medium | K9: =IF(K8="","",IF(K8<1.4,"Low",(IF(AND(K8>=1.4,K8<2.4),"Medium",(IF((AND(K8>=2.4)),"High")))))) -> Medium | M9: =IF(M8="","",IF(M8<1.4,"Low",(IF(AND(M8>=1.4,M8<2.4),"Medium",(IF((AND(M8>=2.4)),"High")))))) -> Low | O9: =IF(O8="","",IF(O8<1.4,"Low",(IF(AND(O8>=1.4,O8<2.4),"Medium",(IF((AND(O8>=2.4)),"High")))))) -> Medium | Q9: =IF(Q8="","",IF(Q8<1.4,"Low",(IF(AND(Q8>=1.4,Q8<2.4),"Medium",(IF((AND(Q8>=2.4)),"High")))))) | S9: =IF(S8="","",IF(S8<1.4,"Low",(IF(AND(S8>=1.4,S8<2.4),"Medium",(IF((AND(S8>=2.4)),"High")))))) | U9: =IF(U8="","",IF(U8<1.4,"Low",(IF(AND(U8>=1.4,U8<2.4),"Medium",(IF((AND(U8>=2.4)),"High")))))) | W9: =IF(W8="","",IF(W8<1.4,"Low",(IF(AND(W8>=1.4,W8<2.4),"Medium",(IF((AND(W8>=2.4)),"High")))))) | Y9: =IF(Y8="","",IF(Y8<1.4,"Low",(IF(AND(Y8>=1.4,Y8<2.4),"Medium",(IF((AND(Y8>=2.4)),"High")))))) | AA9: =IF(AA8="","",IF(AA8<1.4,"Low",(IF(AND(AA8>=1.4,AA8<2.4),"Medium",(IF((AND(AA8>=2.4)),"High")))))) | AC9: =IF(AC8="","",IF(AC8<1.4,"Low",(IF(AND(AC8>=1.4,AC8<2.4),"Medium",(IF((AND(AC8>=2.4)),"High")))))) | AE9: =IF(AE8="","",IF(AE8<1.4,"Low",(IF(AND(AE8>=1.4,AE8<2.4),"Medium",(IF((AND(AE8>=2.4)),"High")))))) | AG9: =IF(AG8="","",IF(AG8<1.4,"Low",(IF(AND(AG8>=1.4,AG8<2.4),"Medium",(IF((AND(AG8>=2.4)),"High")))))) | AI9: =IF(AI8="","",IF(AI8<1.4,"Low",(IF(AND(AI8>=1.4,AI8<2.4),"Medium",(IF((AND(AI8>=2.4)),"High")))))) | AK9: =IF(AK8="","",IF(AK8<1.4,"Low",(IF(AND(AK8>=1.4,AK8<2.4),"Medium",(IF((AND(AK8>=2.4)),"High")))))) | AM9: =IF(AM8="","",IF(AM8<1.4,"Low",(IF(AND(AM8>=1.4,AM8<2.4),"Medium",(IF((AND(AM8>=2.4)),"High")))))) | AO9: =IF(AO8="","",IF(AO8<1.4,"Low",(IF(AND(AO8>=1.4,AO8<2.4),"Medium",(IF((AND(AO8>=2.4)),"High")))))) | AQ9: =IF(AQ8="","",IF(AQ8<1.4,"Low",(IF(AND(AQ8>=1.4,AQ8<2.4),"Medium",(IF((AND(AQ8>=2.4)),"High")))))) | AS9: =IF(AS8="","",IF(AS8<1.4,"Low",(IF(AND(AS8>=1.4,AS8<2.4),"Medium",(IF((AND(AS8>=2.4)),"High")))))) | AU9: =IF(AU8="","",IF(AU8<1.4,"Low",(IF(AND(AU8>=1.4,AU8<2.4),"Medium",(IF((AND(AU8>=2.4)),"High")))))) | AW9: =IF(AW8="","",IF(AW8<1.4,"Low",(IF(AND(AW8>=1.4,AW8<2.4),"Medium",(IF((AND(AW8>=2.4)),"High")))))) | AY9: =IF(AY8="","",IF(AY8<1.4,"Low",(IF(AND(AY8>=1.4,AY8<2.4),"Medium",(IF((AND(AY8>=2.4)),"High")))))) | BA9: =IF(BA8="","",IF(BA8<1.4,"Low",(IF(AND(BA8>=1.4,BA8<2.4),"Medium",(IF((AND(BA8>=2.4)),"High")))))) | BC9: =IF(BC8="","",IF(BC8<1.4,"Low",(IF(AND(BC8>=1.4,BC8<2.4),"Medium",(IF((AND(BC8>=2.4)),"High")))))) | BE9: =IF(BE8="","",IF(BE8<1.4,"Low",(IF(AND(BE8>=1.4,BE8<2.4),"Medium",(IF((AND(BE8>=2.4)),"High")))))) | BG9: =IF(BG8="","",IF(BG8<1.4,"Low",(IF(AND(BG8>=1.4,BG8<2.4),"Medium",(IF((AND(BG8>=2.4)),"High")))))) | BI9: =IF(BI8="","",IF(BI8<1.4,"Low",(IF(AND(BI8>=1.4,BI8<2.4),"Medium",(IF((AND(BI8>=2.4)),"High")))))) | BK9: =IF(BK8="","",IF(BK8<1.4,"Low",(IF(AND(BK8>=1.4,BK8<2.4),"Medium",(IF((AND(BK8>=2.4)),"High"))))))
C11: Override the result / justification
D12: Provide justification in case of the override | E12: =IF(E11>0,"Add justification","") | G12: =IF(G11>0,"Add justification","") | I12: =IF(I11>0,"Add justification","") | O12: Not assessed in previous audit as separate L2 - current assessment rated as Medium | S12: =IF(S11>0,"Add justification","") | U12: =IF(U11>0,"Add justification","") | W12: =IF(W11>0,"Add justification","") | Y12: =IF(Y11>0,"Add justification","") | AA12: =IF(AA11>0,"Add justification","") | AC12: =IF(AC11>0,"Add justification","") | AE12: =IF(AE11>0,"Add justification","") | AG12: =IF(AG11>0,"Add justification","") | AI12: =IF(AI11>0,"Add justification","") | AK12: =IF(AK11>0,"Add justification","") | AM12: =IF(AM11>0,"Add justification","") | AO12: =IF(AO11>0,"Add justification","") | AQ12: =IF(AQ11>0,"Add justification","") | AS12: =IF(AS11>0,"Add justification","") | AU12: =IF(AU11>0,"Add justification","") | AW12: =IF(AW11>0,"Add justification","") | AY12: =IF(AY11>0,"Add justification","") | BA12: =IF(BA11>0,"Add justification","") | BC12: =IF(BC11>0,"Add justification","") | BE12: =IF(BE11>0,"Add justification","") | BG12: =IF(BG11>0,"Add justification","") | BI12: =IF(BI11>0,"Add justification","") | BK12: =IF(BK11>0,"Add justification","")
C13: Result of the last risk assessment (Low, Medium, High) | E13: Medium | G13: Low | I13: Medium | K13: Medium | M13: Low
D14: Provide justification if the risk assessment result changed compared to the previous risk assessment | E14: The risk and impact was Medium in 2024, due to DORA requirements coming into force. From the audit IA concluded DORA requirements had been completed and the risk reduced to low. | G14: As per BCA, L2 was not assessed in Cyber IS audit and current rating is from 2025-001 IT Operations Management Audit.ngs. | I14: No change | K14: No change | M14: As per BCA, L2 was not assessed in current audit. Assessment remains unchanged.

Sheet Dropdown lists
G1: List without none | H1: CMI
A2: High | B2: 3 | C2: X | D2: 1Y | E2: Core | G2: 3 | H2: Weak/undefined | J2: Yes
A3: Medium | B3: 2 | D3: 2Y | E3: Support | G3: 2 | H3: Developed | J3: No
A4: Low | B4: 1 | D4: 3Y | E4: Management | G4: 1 | H4: Strong/Robust
A5: n/a | B5: n/a | E5: Control | G5: n/a
